<?xml version="1.0" encoding="UTF-8" standalone="yes"?>
<Lexicon_Entry Id="001840000000000" Lemma="ἐξεγείρω" Version="0" HasAramaic="false" InLXX="true" AlphaPos="ε">
  <StrongCodes>
    <Strong>G1825</Strong>
  </StrongCodes>
  <Authors/>
  <AlternateLemmas/>
  <MainLinks/>
  <Notes/>
  <ContributorNote/>
  <BaseForms>
    <BaseForm Id="001840001000000">
      <PartsOfSpeech>
        <PartOfSpeech>verb</PartOfSpeech>
      </PartsOfSpeech>
      <Inflections>
        <Inflection Lemma="ἐξεγείρω" BaseFormIndex="1">
          <Form>fut.</Form>
          <Realizations>
            <Realization>ἐξεγερῶ</Realization>
          </Realizations>
          <Comments/>
        </Inflection>
        <Inflection Lemma="ἐξεγείρω" BaseFormIndex="1">
          <Form>aor.</Form>
          <Realizations>
            <Realization>ἐξήγειρα</Realization>
          </Realizations>
          <Comments/>
        </Inflection>
      </Inflections>
      <RelatedLemmas>
        <RelatedLemma>
          <Word>ἐγείρω</Word>
        </RelatedLemma>
      </RelatedLemmas>
      <BaseFormLinks/>
      <LEXMeanings>
        <LEXMeaning Id="001840001001000" IsBiblicalTerm="M" EntryCode="23.94" Indent="0">
          <LEXDomains>
            <LEXDomain>Physiological Processes and States</LEXDomain>
          </LEXDomains>
          <LEXSubDomains>
            <LEXSubDomain>Live, Die</LEXSubDomain>
          </LEXSubDomains>
          <LEXSenses>
            <LEXSense LanguageCode="en" LastEdited="2021-06-04 20:03:37" LastEditedBy="">
              <DefinitionLong/>
              <DefinitionShort>to cause someone to live again after having once died</DefinitionShort>
              <Glosses>
                <Gloss>to raise to life</Gloss>
                <Gloss>to make live again</Gloss>
              </Glosses>
              <Comments/>
            </LEXSense>
          </LEXSenses>
          <LEXReferences>
            <LEXReference>04600601400020</LEXReference>
          </LEXReferences>
          <LEXVideos/>
        </LEXMeaning>
        <LEXMeaning Id="001840001002000" IsBiblicalTerm="Y" EntryCode="13.83" Indent="0">
          <LEXDomains>
            <LEXDomain>Be, Become, Exist, Happen</LEXDomain>
          </LEXDomains>
          <LEXSubDomains>
            <LEXSubDomain>Exist</LEXSubDomain>
          </LEXSubDomains>
          <LEXSenses>
            <LEXSense LanguageCode="en" LastEdited="2021-06-04 20:03:37" LastEditedBy="">
              <DefinitionLong/>
              <DefinitionShort>to cause to come into existence</DefinitionShort>
              <Glosses>
                <Gloss>to cause to exist</Gloss>
                <Gloss>to provide</Gloss>
                <Gloss>to raise up</Gloss>
              </Glosses>
              <Comments>For another interpretation of ἐξεγείρω in {S:04500901700022}, see {D:87.38}.</Comments>
            </LEXSense>
          </LEXSenses>
          <LEXReferences>
            <LEXReference>04500901700022</LEXReference>
          </LEXReferences>
          <LEXVideos/>
        </LEXMeaning>
        <LEXMeaning Id="001840001003000" IsBiblicalTerm="Y" EntryCode="87.38" Indent="0">
          <LEXDomains>
            <LEXDomain>Status</LEXDomain>
          </LEXDomains>
          <LEXSubDomains>
            <LEXSubDomain>High Status or Rank [including persons of high status]</LEXSubDomain>
          </LEXSubDomains>
          <LEXSenses>
            <LEXSense LanguageCode="en" LastEdited="2021-06-04 20:03:37" LastEditedBy="">
              <DefinitionLong/>
              <DefinitionShort>to cause someone to have a higher position and status</DefinitionShort>
              <Glosses>
                <Gloss>to give higher status to</Gloss>
                <Gloss>to raise up</Gloss>
                <Gloss>to exalt</Gloss>
              </Glosses>
              <Comments>For another interpretation of ἐξεγείρω in {S:04500901700022}, see {D:13.83}.</Comments>
            </LEXSense>
          </LEXSenses>
          <LEXReferences>
            <LEXReference>04500901700022</LEXReference>
          </LEXReferences>
          <LEXVideos/>
        </LEXMeaning>
      </LEXMeanings>
    </BaseForm>
  </BaseForms>
</Lexicon_Entry>