<?xml version="1.0" encoding="UTF-8" standalone="yes"?>
<Lexicon_Entry Id="004976000000000" Lemma="τεφρόω" Version="0" HasAramaic="false" InLXX="false" AlphaPos="τ">
  <StrongCodes>
    <Strong>G5077</Strong>
  </StrongCodes>
  <Authors/>
  <AlternateLemmas/>
  <MainLinks/>
  <Notes/>
  <ContributorNote/>
  <BaseForms>
    <BaseForm Id="004976001000000">
      <PartsOfSpeech>
        <PartOfSpeech>verb</PartOfSpeech>
      </PartsOfSpeech>
      <RelatedLemmas>
        <RelatedLemma>
          <Word>τύφομαι</Word>
        </RelatedLemma>
      </RelatedLemmas>
      <BaseFormLinks/>
      <LEXMeanings>
        <LEXMeaning Id="004976001001000" IsBiblicalTerm="Y" EntryCode="14.72" Indent="0">
          <LEXDomains>
            <LEXDomain>Physical Events and States</LEXDomain>
          </LEXDomains>
          <LEXSubDomains>
            <LEXSubDomain>Burning</LEXSubDomain>
          </LEXSubDomains>
          <LEXSenses>
            <LEXSense LanguageCode="en" LastEdited="2022-04-05 14:32:37" LastEditedBy="">
              <DefinitionLong/>
              <DefinitionShort>(derivative of τέφρα ‘ashes,’ not occurring in the NT) to destroy by reducing something to ashes</DefinitionShort>
              <Glosses>
                <Gloss>to reduce to ashes</Gloss>
              </Glosses>
              <Comments>It is possible to render ‘to reduce to ashes’ as ‘to burn up completely’ or ‘to destroy by fire and leave only ashes.’</Comments>
            </LEXSense>
          </LEXSenses>
          <LEXReferences>
            <LEXReference>06100200600012</LEXReference>
          </LEXReferences>
          <LEXVideos/>
        </LEXMeaning>
      </LEXMeanings>
    </BaseForm>
  </BaseForms>
</Lexicon_Entry>