<?xml version="1.0" encoding="UTF-8" standalone="yes"?>
<Lexicon_Entry Id="000003000000000" Lemma="אָב" Version="5" HasAramaic="false" InLXX="false" AlphaPos="א">
  <StrongCodes>
    <Strong>H0001</Strong>
  </StrongCodes>
  <Authors>
    <Author>Reinier de Blois</Author>
  </Authors>
  <Contributors/>
  <AlternateLemmas/>
  <MainLinks/>
  <Notes>
    <Note Caller="1" LanguageCode="en" LastEdited="" LastEditedBy="">
      <References>
        <Reference>00901201500040</Reference>
      </References>
      <Content>{A:MT} {A:HOTTP}-B {A:NIV} {A:NJPS} | {A:LXX} {A:RSV} {A:NJB} {A:NRSV} {A:REB} {A:GNT} {A:CEV} "and your king"</Content>
    </Note>
    <Note Caller="2" LanguageCode="en" LastEdited="" LastEditedBy="">
      <References>
        <Reference>01300400300006</Reference>
      </References>
      <Content>{A:MT} {A:HOTTP}-C | {A:NJPS} "[the sons of] the father of" |{A:RSV} {A:NIV} {A:NRSV} {A:REB} {A:GNT} {A:CEV} "sons of" | {A:NJB} "Abi-Etam"</Content>
    </Note>
  </Notes>
  <ContributorNote/>
  <BaseForms>
    <BaseForm Id="000003001000000">
      <PartsOfSpeech>
        <PartOfSpeech>nsm</PartOfSpeech>
      </PartsOfSpeech>
      <RelatedNames>
        <RelatedName>
          <Word>אֲבִי</Word>
        </RelatedName>
        <RelatedName>
          <Word>אֲבִיאֵל</Word>
        </RelatedName>
        <RelatedName>
          <Word>אֲבִיאָסָף</Word>
        </RelatedName>
        <RelatedName>
          <Word>אֲבִיגַיִל</Word>
        </RelatedName>
        <RelatedName>
          <Word>אֲבִיגַל</Word>
        </RelatedName>
        <RelatedName>
          <Word>אֲבִידָן</Word>
        </RelatedName>
        <RelatedName>
          <Word>אֲבִיָּה</Word>
        </RelatedName>
        <RelatedName>
          <Word>אֲבִיהוּא</Word>
        </RelatedName>
        <RelatedName>
          <Word>אֲבִיהוּד</Word>
        </RelatedName>
        <RelatedName>
          <Word>אֲבִיהַיִל</Word>
        </RelatedName>
        <RelatedName>
          <Word>אֲבִיחַיִל</Word>
        </RelatedName>
        <RelatedName>
          <Word>אֲבִיטוּב</Word>
        </RelatedName>
        <RelatedName>
          <Word>אֲבִיטַל</Word>
        </RelatedName>
        <RelatedName>
          <Word>אֲבִיָּם</Word>
        </RelatedName>
        <RelatedName>
          <Word>אֲבִימָאֵל</Word>
        </RelatedName>
        <RelatedName>
          <Word>אֲבִימֶלֶךְ</Word>
        </RelatedName>
        <RelatedName>
          <Word>אֲבִינָדָב</Word>
        </RelatedName>
        <RelatedName>
          <Word>אֲבִינֹעַם</Word>
        </RelatedName>
        <RelatedName>
          <Word>אֶבְיָסָף</Word>
        </RelatedName>
        <RelatedName>
          <Word>אֲבִיעֶזֶר</Word>
        </RelatedName>
        <RelatedName>
          <Word>אֲבִי־עַלְבֹון</Word>
        </RelatedName>
        <RelatedName>
          <Word>אֲבִירָם</Word>
        </RelatedName>
        <RelatedName>
          <Word>אֲבִישַׁג</Word>
        </RelatedName>
        <RelatedName>
          <Word>אֲבִישׁוּעַ</Word>
        </RelatedName>
        <RelatedName>
          <Word>אֲבִישַׁי</Word>
        </RelatedName>
        <RelatedName>
          <Word>אֲבִישָׁלֹום</Word>
        </RelatedName>
        <RelatedName>
          <Word>אֶבְיָתָר</Word>
        </RelatedName>
        <RelatedName>
          <Word>אַבְנֵר</Word>
        </RelatedName>
        <RelatedName>
          <Word>אַבְרָהָם</Word>
        </RelatedName>
        <RelatedName>
          <Word>אַבְרָם</Word>
        </RelatedName>
        <RelatedName>
          <Word>אַבְשָׁלֹום</Word>
        </RelatedName>
        <RelatedName>
          <Word>יֶשֶׁבְאָב</Word>
        </RelatedName>
      </RelatedNames>
      <BaseFormLinks/>
      <LEXMeanings>
        <LEXMeaning Id="000003001001000" IsBiblicalTerm="M" EntryCode="" Indent="0">
          <LEXDomains>
            <LEXDomain Code="001001002003012">Relatives</LEXDomain>
          </LEXDomains>
          <LEXSenses>
            <LEXSense LanguageCode="en" LastEdited="2017-12-31 13:15:24" LastEditedBy="">
              <DefinitionLong/>
              <DefinitionShort>= direct male progenitor; ► who normally provides protection, care, instruction, and discipline; ≈ is usually regarded with respect and associated with wisdom, security, and comfort</DefinitionShort>
              <Glosses>
                <Gloss>father</Gloss>
              </Glosses>
              <Comments/>
            </LEXSense>
          </LEXSenses>
          <LEXReferences>
            <LEXReference>00100202400012</LEXReference>
            <LEXReference>00100902200016</LEXReference>
            <LEXReference>00100902300042</LEXReference>
            <LEXReference>00100902300054</LEXReference>
            <LEXReference>00101102800014</LEXReference>
            <LEXReference>00101102900038</LEXReference>
            <LEXReference>00101102900044</LEXReference>
            <LEXReference>00101903100016</LEXReference>
            <LEXReference>00101903200008</LEXReference>
            <LEXReference>00101903200024</LEXReference>
            <LEXReference>00101903300008</LEXReference>
            <LEXReference>00101903300034</LEXReference>
            <LEXReference>00101903400032</LEXReference>
            <LEXReference>00101903400058</LEXReference>
            <LEXReference>00101903500020</LEXReference>
            <LEXReference>00101903600014</LEXReference>
            <LEXReference>00102001200012</LEXReference>
            <LEXReference>00102200700012</LEXReference>
            <LEXReference>00102200700018</LEXReference>
            <LEXReference>00102600300066</LEXReference>
            <LEXReference>00102601500016</LEXReference>
            <LEXReference>00102601500024</LEXReference>
            <LEXReference>00102601800030</LEXReference>
            <LEXReference>00102601800064</LEXReference>
            <LEXReference>00102602400030</LEXReference>
            <LEXReference>00102700600024</LEXReference>
            <LEXReference>00102700900040</LEXReference>
            <LEXReference>00102701000008</LEXReference>
            <LEXReference>00102701200006</LEXReference>
            <LEXReference>00102701400032</LEXReference>
            <LEXReference>00102701800008</LEXReference>
            <LEXReference>00102701800014</LEXReference>
            <LEXReference>00102701900010</LEXReference>
            <LEXReference>00102702200012</LEXReference>
            <LEXReference>00102702600010</LEXReference>
            <LEXReference>00102703000042</LEXReference>
            <LEXReference>00102703100018</LEXReference>
            <LEXReference>00102703100026</LEXReference>
            <LEXReference>00102703100030</LEXReference>
            <LEXReference>00102703200010</LEXReference>
            <LEXReference>00102703400012</LEXReference>
            <LEXReference>00102703400036</LEXReference>
            <LEXReference>00102703400044</LEXReference>
            <LEXReference>00102703800010</LEXReference>
            <LEXReference>00102703800022</LEXReference>
            <LEXReference>00102703800030</LEXReference>
            <LEXReference>00102703900008</LEXReference>
            <LEXReference>00102704100022</LEXReference>
            <LEXReference>00102704100040</LEXReference>
            <LEXReference>00102800200014</LEXReference>
            <LEXReference>00102800700010</LEXReference>
            <LEXReference>00102800800022</LEXReference>
            <LEXReference>00102900900024</LEXReference>
            <LEXReference>00102901200016</LEXReference>
            <LEXReference>00102901200040</LEXReference>
            <LEXReference>00103100100030</LEXReference>
            <LEXReference>00103100100040</LEXReference>
            <LEXReference>00103100500016</LEXReference>
            <LEXReference>00103100500034</LEXReference>
            <LEXReference>00103100600020</LEXReference>
            <LEXReference>00103100700004</LEXReference>
            <LEXReference>00103100900012</LEXReference>
            <LEXReference>00103101600018</LEXReference>
            <LEXReference>00103101800046</LEXReference>
            <LEXReference>00103101900032</LEXReference>
            <LEXReference>00103102900022</LEXReference>
            <LEXReference>00103103500008</LEXReference>
            <LEXReference>00103104200006</LEXReference>
            <LEXReference>00103105300018</LEXReference>
            <LEXReference>00103105300030</LEXReference>
            <LEXReference>00103201000018</LEXReference>
            <LEXReference>00103400400012</LEXReference>
            <LEXReference>00103400600008</LEXReference>
            <LEXReference>00103401100010</LEXReference>
            <LEXReference>00103401300020</LEXReference>
            <LEXReference>00103501800026</LEXReference>
            <LEXReference>00103502200038</LEXReference>
            <LEXReference>00103502700012</LEXReference>
            <LEXReference>00103602400052</LEXReference>
            <LEXReference>00103700100014</LEXReference>
            <LEXReference>00103700200054</LEXReference>
            <LEXReference>00103700200070</LEXReference>
            <LEXReference>00103700400014</LEXReference>
            <LEXReference>00103701000008</LEXReference>
            <LEXReference>00103701000022</LEXReference>
            <LEXReference>00103701100012</LEXReference>
            <LEXReference>00103701200016</LEXReference>
            <LEXReference>00103702200064</LEXReference>
            <LEXReference>00103703200020</LEXReference>
            <LEXReference>00103703500050</LEXReference>
            <LEXReference>00104201300038</LEXReference>
            <LEXReference>00104202900010</LEXReference>
            <LEXReference>00104203200012</LEXReference>
            <LEXReference>00104203200032</LEXReference>
            <LEXReference>00104203500040</LEXReference>
            <LEXReference>00104203600010</LEXReference>
            <LEXReference>00104203700010</LEXReference>
            <LEXReference>00104300200036</LEXReference>
            <LEXReference>00104300700030</LEXReference>
            <LEXReference>00104300800012</LEXReference>
            <LEXReference>00104301100010</LEXReference>
            <LEXReference>00104302300020</LEXReference>
            <LEXReference>00104302700020</LEXReference>
            <LEXReference>00104302800014</LEXReference>
            <LEXReference>00104401700052</LEXReference>
            <LEXReference>00104401900020</LEXReference>
            <LEXReference>00104402000014</LEXReference>
            <LEXReference>00104402000048</LEXReference>
            <LEXReference>00104402200024</LEXReference>
            <LEXReference>00104402200032</LEXReference>
            <LEXReference>00104402400014</LEXReference>
            <LEXReference>00104402500006</LEXReference>
            <LEXReference>00104402700008</LEXReference>
            <LEXReference>00104403000014</LEXReference>
            <LEXReference>00104403100034</LEXReference>
            <LEXReference>00104403200018</LEXReference>
            <LEXReference>00104403200038</LEXReference>
            <LEXReference>00104403400010</LEXReference>
            <LEXReference>00104403400038</LEXReference>
            <LEXReference>00104500300020</LEXReference>
            <LEXReference>00104500900010</LEXReference>
            <LEXReference>00104501300008</LEXReference>
            <LEXReference>00104501300040</LEXReference>
            <LEXReference>00104501800008</LEXReference>
            <LEXReference>00104501900040</LEXReference>
            <LEXReference>00104502300006</LEXReference>
            <LEXReference>00104502300046</LEXReference>
            <LEXReference>00104502500022</LEXReference>
            <LEXReference>00104502700052</LEXReference>
            <LEXReference>00104600100034</LEXReference>
            <LEXReference>00104600300014</LEXReference>
            <LEXReference>00104600500026</LEXReference>
            <LEXReference>00104602900020</LEXReference>
            <LEXReference>00104700100020</LEXReference>
            <LEXReference>00104700500016</LEXReference>
            <LEXReference>00104700600024</LEXReference>
            <LEXReference>00104700700012</LEXReference>
            <LEXReference>00104701100010</LEXReference>
            <LEXReference>00104701200010</LEXReference>
            <LEXReference>00104800100026</LEXReference>
            <LEXReference>00104800900010</LEXReference>
            <LEXReference>00104801600038</LEXReference>
            <LEXReference>00104801700012</LEXReference>
            <LEXReference>00104801700038</LEXReference>
            <LEXReference>00104801800010</LEXReference>
            <LEXReference>00104801800016</LEXReference>
            <LEXReference>00104801900006</LEXReference>
            <LEXReference>00104900200020</LEXReference>
            <LEXReference>00104900400020</LEXReference>
            <LEXReference>00104900800024</LEXReference>
            <LEXReference>00104902500006</LEXReference>
            <LEXReference>00104902600004</LEXReference>
            <LEXReference>00104902800024</LEXReference>
            <LEXReference>00105000100012</LEXReference>
            <LEXReference>00105000200024</LEXReference>
            <LEXReference>00105000500002</LEXReference>
            <LEXReference>00105000500050</LEXReference>
            <LEXReference>00105000600016</LEXReference>
            <LEXReference>00105000700014</LEXReference>
            <LEXReference>00105001000046</LEXReference>
            <LEXReference>00105001400032</LEXReference>
            <LEXReference>00105001400040</LEXReference>
            <LEXReference>00105001500014</LEXReference>
            <LEXReference>00105001600014</LEXReference>
            <LEXReference>00105001700046</LEXReference>
            <LEXReference>00200201600038</LEXReference>
            <LEXReference>00200201800010</LEXReference>
            <LEXReference>00201000600030</LEXReference>
            <LEXReference>00201000600034</LEXReference>
            <LEXReference>00201000600036</LEXReference>
            <LEXReference>00201800400016</LEXReference>
            <LEXReference>00202000500030</LEXReference>
            <LEXReference>00202001200006</LEXReference>
            <LEXReference>00202101500006</LEXReference>
            <LEXReference>00202101700006</LEXReference>
            <LEXReference>00202201600008</LEXReference>
            <LEXReference>00203400700036</LEXReference>
            <LEXReference>00204001500016</LEXReference>
            <LEXReference>00301603200032</LEXReference>
            <LEXReference>00301800700004</LEXReference>
            <LEXReference>00301800800006</LEXReference>
            <LEXReference>00301800800014</LEXReference>
            <LEXReference>00301800900008</LEXReference>
            <LEXReference>00301801100008</LEXReference>
            <LEXReference>00301801100012</LEXReference>
            <LEXReference>00301801200006</LEXReference>
            <LEXReference>00301801200014</LEXReference>
            <LEXReference>00301801400006</LEXReference>
            <LEXReference>00301900300008</LEXReference>
            <LEXReference>00302000900014</LEXReference>
            <LEXReference>00302000900026</LEXReference>
            <LEXReference>00302001100014</LEXReference>
            <LEXReference>00302001100018</LEXReference>
            <LEXReference>00302001700016</LEXReference>
            <LEXReference>00302001900014</LEXReference>
            <LEXReference>00302100200024</LEXReference>
            <LEXReference>00302100900020</LEXReference>
            <LEXReference>00302101100018</LEXReference>
            <LEXReference>00302201300044</LEXReference>
            <LEXReference>00400300400064</LEXReference>
            <LEXReference>00400600700004</LEXReference>
            <LEXReference>00401201400014</LEXReference>
            <LEXReference>00401401800034</LEXReference>
            <LEXReference>00402700300002</LEXReference>
            <LEXReference>00402700400008</LEXReference>
            <LEXReference>00402700400036</LEXReference>
            <LEXReference>00402700700026</LEXReference>
            <LEXReference>00402700700036</LEXReference>
            <LEXReference>00402701000024</LEXReference>
            <LEXReference>00402701100012</LEXReference>
            <LEXReference>00403000500006</LEXReference>
            <LEXReference>00403000500030</LEXReference>
            <LEXReference>00403000600008</LEXReference>
            <LEXReference>00403000600050</LEXReference>
            <LEXReference>00403001700028</LEXReference>
            <LEXReference>00403201400010</LEXReference>
            <LEXReference>00403601200032</LEXReference>
            <LEXReference>00500500900030</LEXReference>
            <LEXReference>00500501600006</LEXReference>
            <LEXReference>00502101300030</LEXReference>
            <LEXReference>00502101800026</LEXReference>
            <LEXReference>00502101900008</LEXReference>
            <LEXReference>00502201500006</LEXReference>
            <LEXReference>00502201600006</LEXReference>
            <LEXReference>00502201900018</LEXReference>
            <LEXReference>00502202100022</LEXReference>
            <LEXReference>00502202100058</LEXReference>
            <LEXReference>00502202900018</LEXReference>
            <LEXReference>00502300100012</LEXReference>
            <LEXReference>00502300100022</LEXReference>
            <LEXReference>00502401600006</LEXReference>
            <LEXReference>00502401600022</LEXReference>
            <LEXReference>00502701600006</LEXReference>
            <LEXReference>00502702000010</LEXReference>
            <LEXReference>00502702000018</LEXReference>
            <LEXReference>00502702200012</LEXReference>
            <LEXReference>00503200700020</LEXReference>
            <LEXReference>00503300900008</LEXReference>
            <LEXReference>00600201300008</LEXReference>
            <LEXReference>00600201800046</LEXReference>
            <LEXReference>00600402100026</LEXReference>
            <LEXReference>00600602300026</LEXReference>
            <LEXReference>00601501300038</LEXReference>
            <LEXReference>00601501800022</LEXReference>
            <LEXReference>00601700400084</LEXReference>
            <LEXReference>00601905100032</LEXReference>
            <LEXReference>00602101100012</LEXReference>
            <LEXReference>00602400200044</LEXReference>
            <LEXReference>00602400200050</LEXReference>
            <LEXReference>00700101400022</LEXReference>
            <LEXReference>00700602500038</LEXReference>
            <LEXReference>00700602500068</LEXReference>
            <LEXReference>00700803200028</LEXReference>
            <LEXReference>00700900500008</LEXReference>
            <LEXReference>00700901700006</LEXReference>
            <LEXReference>00700905600020</LEXReference>
            <LEXReference>00701103600008</LEXReference>
            <LEXReference>00701103700008</LEXReference>
            <LEXReference>00701103900020</LEXReference>
            <LEXReference>00701400200012</LEXReference>
            <LEXReference>00701400300008</LEXReference>
            <LEXReference>00701400300062</LEXReference>
            <LEXReference>00701400400004</LEXReference>
            <LEXReference>00701400500010</LEXReference>
            <LEXReference>00701400600042</LEXReference>
            <LEXReference>00701400900026</LEXReference>
            <LEXReference>00701401000006</LEXReference>
            <LEXReference>00701401600056</LEXReference>
            <LEXReference>00701401900064</LEXReference>
            <LEXReference>00701500100054</LEXReference>
            <LEXReference>00701500200006</LEXReference>
            <LEXReference>00701500600058</LEXReference>
            <LEXReference>00701603100048</LEXReference>
            <LEXReference>00701900300048</LEXReference>
            <LEXReference>00701900300054</LEXReference>
            <LEXReference>00701900400010</LEXReference>
            <LEXReference>00701900500038</LEXReference>
            <LEXReference>00701900600022</LEXReference>
            <LEXReference>00701900800030</LEXReference>
            <LEXReference>00701900900032</LEXReference>
            <LEXReference>00702102200010</LEXReference>
            <LEXReference>00800201100040</LEXReference>
            <LEXReference>00800401700036</LEXReference>
            <LEXReference>00800401700040</LEXReference>
            <LEXReference>00900202500046</LEXReference>
            <LEXReference>00900900300014</LEXReference>
            <LEXReference>00900900500036</LEXReference>
            <LEXReference>00901000200064</LEXReference>
            <LEXReference>00901001200020</LEXReference>
            <LEXReference>00901400100056</LEXReference>
            <LEXReference>00901402700014</LEXReference>
            <LEXReference>00901402800022</LEXReference>
            <LEXReference>00901402900010</LEXReference>
            <LEXReference>00901405100006</LEXReference>
            <LEXReference>00901405100014</LEXReference>
            <LEXReference>00901701500026</LEXReference>
            <LEXReference>00901703400020</LEXReference>
            <LEXReference>00901801800024</LEXReference>
            <LEXReference>00901900200020</LEXReference>
            <LEXReference>00901900300016</LEXReference>
            <LEXReference>00901900300040</LEXReference>
            <LEXReference>00901900400018</LEXReference>
            <LEXReference>00902000100054</LEXReference>
            <LEXReference>00902000200024</LEXReference>
            <LEXReference>00902000200052</LEXReference>
            <LEXReference>00902000300018</LEXReference>
            <LEXReference>00902000600008</LEXReference>
            <LEXReference>00902000800046</LEXReference>
            <LEXReference>00902000900032</LEXReference>
            <LEXReference>00902001000024</LEXReference>
            <LEXReference>00902001200024</LEXReference>
            <LEXReference>00902001300024</LEXReference>
            <LEXReference>00902001300070</LEXReference>
            <LEXReference>00902003200012</LEXReference>
            <LEXReference>00902003300036</LEXReference>
            <LEXReference>00902003400054</LEXReference>
            <LEXReference>00902200300030</LEXReference>
            <LEXReference>00902201500046</LEXReference>
            <LEXReference>00902301700022</LEXReference>
            <LEXReference>00902301700052</LEXReference>
            <LEXReference>01000203200018</LEXReference>
            <LEXReference>01000300700036</LEXReference>
            <LEXReference>01000300800050</LEXReference>
            <LEXReference>01000602100026</LEXReference>
            <LEXReference>01000900700030</LEXReference>
            <LEXReference>01000900700046</LEXReference>
            <LEXReference>01001000200026</LEXReference>
            <LEXReference>01001000200050</LEXReference>
            <LEXReference>01001000300026</LEXReference>
            <LEXReference>01001300500024</LEXReference>
            <LEXReference>01001503400032</LEXReference>
            <LEXReference>01001601900036</LEXReference>
            <LEXReference>01001602100018</LEXReference>
            <LEXReference>01001602100046</LEXReference>
            <LEXReference>01001602200030</LEXReference>
            <LEXReference>01001700800014</LEXReference>
            <LEXReference>01001700800050</LEXReference>
            <LEXReference>01001701000040</LEXReference>
            <LEXReference>01001702300066</LEXReference>
            <LEXReference>01001903800020</LEXReference>
            <LEXReference>01002101400034</LEXReference>
            <LEXReference>01100100600008</LEXReference>
            <LEXReference>01100201200014</LEXReference>
            <LEXReference>01100202400028</LEXReference>
            <LEXReference>01100202600068</LEXReference>
            <LEXReference>01100202600084</LEXReference>
            <LEXReference>01100203200046</LEXReference>
            <LEXReference>01100204400040</LEXReference>
            <LEXReference>01100300300022</LEXReference>
            <LEXReference>01100300600018</LEXReference>
            <LEXReference>01100300700022</LEXReference>
            <LEXReference>01100301400030</LEXReference>
            <LEXReference>01100501500036</LEXReference>
            <LEXReference>01100501700010</LEXReference>
            <LEXReference>01100501900034</LEXReference>
            <LEXReference>01100601200066</LEXReference>
            <LEXReference>01100701400018</LEXReference>
            <LEXReference>01100705100038</LEXReference>
            <LEXReference>01100801500026</LEXReference>
            <LEXReference>01100801700012</LEXReference>
            <LEXReference>01100801800012</LEXReference>
            <LEXReference>01100802000024</LEXReference>
            <LEXReference>01100802400012</LEXReference>
            <LEXReference>01100802500020</LEXReference>
            <LEXReference>01100802600028</LEXReference>
            <LEXReference>01100900400022</LEXReference>
            <LEXReference>01100900500030</LEXReference>
            <LEXReference>01101100400050</LEXReference>
            <LEXReference>01101100600032</LEXReference>
            <LEXReference>01101101200016</LEXReference>
            <LEXReference>01101101700020</LEXReference>
            <LEXReference>01101102700042</LEXReference>
            <LEXReference>01101103300074</LEXReference>
            <LEXReference>01101104300022</LEXReference>
            <LEXReference>01101200400002</LEXReference>
            <LEXReference>01101200400022</LEXReference>
            <LEXReference>01101200600030</LEXReference>
            <LEXReference>01101200900052</LEXReference>
            <LEXReference>01101201000046</LEXReference>
            <LEXReference>01101201000078</LEXReference>
            <LEXReference>01101201100006</LEXReference>
            <LEXReference>01101201100026</LEXReference>
            <LEXReference>01101201400020</LEXReference>
            <LEXReference>01101201400038</LEXReference>
            <LEXReference>01101301100076</LEXReference>
            <LEXReference>01101301200008</LEXReference>
            <LEXReference>01101500300012</LEXReference>
            <LEXReference>01101501500010</LEXReference>
            <LEXReference>01101501900012</LEXReference>
            <LEXReference>01101501900018</LEXReference>
            <LEXReference>01101902000030</LEXReference>
            <LEXReference>01102003400016</LEXReference>
            <LEXReference>01102003400022</LEXReference>
            <LEXReference>01102003400044</LEXReference>
            <LEXReference>01102204300014</LEXReference>
            <LEXReference>01102204700020</LEXReference>
            <LEXReference>01102205300024</LEXReference>
            <LEXReference>01102205400038</LEXReference>
            <LEXReference>01200300200022</LEXReference>
            <LEXReference>01200300200046</LEXReference>
            <LEXReference>01200301300028</LEXReference>
            <LEXReference>01200401800024</LEXReference>
            <LEXReference>01200401900008</LEXReference>
            <LEXReference>01200902500050</LEXReference>
            <LEXReference>01201000300030</LEXReference>
            <LEXReference>01201302500042</LEXReference>
            <LEXReference>01201400300036</LEXReference>
            <LEXReference>01201400500038</LEXReference>
            <LEXReference>01201400600044</LEXReference>
            <LEXReference>01201400600060</LEXReference>
            <LEXReference>01201402100036</LEXReference>
            <LEXReference>01201500300026</LEXReference>
            <LEXReference>01201503400026</LEXReference>
            <LEXReference>01202100300022</LEXReference>
            <LEXReference>01202102000024</LEXReference>
            <LEXReference>01202102100018</LEXReference>
            <LEXReference>01202102100034</LEXReference>
            <LEXReference>01202303000060</LEXReference>
            <LEXReference>01202303400022</LEXReference>
            <LEXReference>01202400900024</LEXReference>
            <LEXReference>01300201700014</LEXReference>
            <LEXReference>01300204400012</LEXReference>
            <LEXReference>01300401700042</LEXReference>
            <LEXReference>01300401900014</LEXReference>
            <LEXReference>01300500100028</LEXReference>
            <LEXReference>01300702200008</LEXReference>
            <LEXReference>01301900200024</LEXReference>
            <LEXReference>01301900200044</LEXReference>
            <LEXReference>01301900300024</LEXReference>
            <LEXReference>01302400200016</LEXReference>
            <LEXReference>01302500300032</LEXReference>
            <LEXReference>01302500600010</LEXReference>
            <LEXReference>01302601000034</LEXReference>
            <LEXReference>01302800400068</LEXReference>
            <LEXReference>01302800900016</LEXReference>
            <LEXReference>01302902300022</LEXReference>
            <LEXReference>01400100800020</LEXReference>
            <LEXReference>01400100900016</LEXReference>
            <LEXReference>01400200200030</LEXReference>
            <LEXReference>01400200600100</LEXReference>
            <LEXReference>01400201300014</LEXReference>
            <LEXReference>01400201300132</LEXReference>
            <LEXReference>01400201600038</LEXReference>
            <LEXReference>01400300100038</LEXReference>
            <LEXReference>01400500100036</LEXReference>
            <LEXReference>01400600400026</LEXReference>
            <LEXReference>01400600700012</LEXReference>
            <LEXReference>01400600800012</LEXReference>
            <LEXReference>01400601000024</LEXReference>
            <LEXReference>01400601500012</LEXReference>
            <LEXReference>01400601600020</LEXReference>
            <LEXReference>01400701700022</LEXReference>
            <LEXReference>01400701800022</LEXReference>
            <LEXReference>01400801400012</LEXReference>
            <LEXReference>01400903100022</LEXReference>
            <LEXReference>01401000400002</LEXReference>
            <LEXReference>01401000400020</LEXReference>
            <LEXReference>01401000600030</LEXReference>
            <LEXReference>01401000900052</LEXReference>
            <LEXReference>01401001000042</LEXReference>
            <LEXReference>01401001000074</LEXReference>
            <LEXReference>01401001100006</LEXReference>
            <LEXReference>01401001100026</LEXReference>
            <LEXReference>01401001400034</LEXReference>
            <LEXReference>01401501800010</LEXReference>
            <LEXReference>01401600300014</LEXReference>
            <LEXReference>01401600300020</LEXReference>
            <LEXReference>01401700200046</LEXReference>
            <LEXReference>01401700300022</LEXReference>
            <LEXReference>01401700400008</LEXReference>
            <LEXReference>01402003200010</LEXReference>
            <LEXReference>01402100300008</LEXReference>
            <LEXReference>01402100400012</LEXReference>
            <LEXReference>01402101200048</LEXReference>
            <LEXReference>01402200400036</LEXReference>
            <LEXReference>01402402200024</LEXReference>
            <LEXReference>01402500300036</LEXReference>
            <LEXReference>01402500400046</LEXReference>
            <LEXReference>01402500400062</LEXReference>
            <LEXReference>01402600100036</LEXReference>
            <LEXReference>01402600400026</LEXReference>
            <LEXReference>01402700200026</LEXReference>
            <LEXReference>01403300300022</LEXReference>
            <LEXReference>01403302200024</LEXReference>
            <LEXReference>01403302200042</LEXReference>
            <LEXReference>01403302300022</LEXReference>
            <LEXReference>01403600100026</LEXReference>
            <LEXReference>01700200700026</LEXReference>
            <LEXReference>01700200700054</LEXReference>
            <LEXReference>01801501000016</LEXReference>
            <LEXReference>01803000100022</LEXReference>
            <LEXReference>01803101800012</LEXReference>
            <LEXReference>01804201500032</LEXReference>
            <LEXReference>01902701000004</LEXReference>
            <LEXReference>01910301300006</LEXReference>
            <LEXReference>02000100800008</LEXReference>
            <LEXReference>02000301200018</LEXReference>
            <LEXReference>02000400100008</LEXReference>
            <LEXReference>02000400300010</LEXReference>
            <LEXReference>02000602000008</LEXReference>
            <LEXReference>02001000100012</LEXReference>
            <LEXReference>02001300100008</LEXReference>
            <LEXReference>02001500500008</LEXReference>
            <LEXReference>02001502000008</LEXReference>
            <LEXReference>02001700600016</LEXReference>
            <LEXReference>02001702100018</LEXReference>
            <LEXReference>02001702500006</LEXReference>
            <LEXReference>02001901300006</LEXReference>
            <LEXReference>02001902600004</LEXReference>
            <LEXReference>02002002000004</LEXReference>
            <LEXReference>02002302200006</LEXReference>
            <LEXReference>02002302400010</LEXReference>
            <LEXReference>02002302500004</LEXReference>
            <LEXReference>02002701000012</LEXReference>
            <LEXReference>02002800700018</LEXReference>
            <LEXReference>02002802400004</LEXReference>
            <LEXReference>02002900300010</LEXReference>
            <LEXReference>02003001100004</LEXReference>
            <LEXReference>02003001700008</LEXReference>
            <LEXReference>02300800400016</LEXReference>
            <LEXReference>02303801900016</LEXReference>
            <LEXReference>02304501000008</LEXReference>
            <LEXReference>02400602100032</LEXReference>
            <LEXReference>02400701800014</LEXReference>
            <LEXReference>02401301400016</LEXReference>
            <LEXReference>02401600300054</LEXReference>
            <LEXReference>02401600700036</LEXReference>
            <LEXReference>02402001500014</LEXReference>
            <LEXReference>02402201100030</LEXReference>
            <LEXReference>02402201500018</LEXReference>
            <LEXReference>02403102900018</LEXReference>
            <LEXReference>02403201800016</LEXReference>
            <LEXReference>02404700300028</LEXReference>
            <LEXReference>02500500300014</LEXReference>
            <LEXReference>02600501000004</LEXReference>
            <LEXReference>02600501000020</LEXReference>
            <LEXReference>02601800200030</LEXReference>
            <LEXReference>02601800400020</LEXReference>
            <LEXReference>02601801400020</LEXReference>
            <LEXReference>02601801700040</LEXReference>
            <LEXReference>02601801800002</LEXReference>
            <LEXReference>02601801900022</LEXReference>
            <LEXReference>02601802000026</LEXReference>
            <LEXReference>02601802000030</LEXReference>
            <LEXReference>02602200700002</LEXReference>
            <LEXReference>02602201000004</LEXReference>
            <LEXReference>02602201100040</LEXReference>
            <LEXReference>02604402500024</LEXReference>
            <LEXReference>03000200700032</LEXReference>
            <LEXReference>03300700600008</LEXReference>
            <LEXReference>03801300300020</LEXReference>
            <LEXReference>03801300300048</LEXReference>
            <LEXReference>03900100600006</LEXReference>
            <LEXReference>03900302400008</LEXReference>
            <LEXReference>03900302400022</LEXReference>
          </LEXReferences>
          <LEXVideos/>
          <LEXCoreDomains>
            <LEXCoreDomain Code="062">Family</LEXCoreDomain>
            <LEXCoreDomain Code="121">Parenthood</LEXCoreDomain>
            <LEXCoreDomain Code="129">Posterity</LEXCoreDomain>
          </LEXCoreDomains>
        </LEXMeaning>
        <LEXMeaning Id="000003001002000" IsBiblicalTerm="M" EntryCode="" Indent="0">
          <LEXDomains>
            <LEXDomain Code="001001002003012">Relatives</LEXDomain>
          </LEXDomains>
          <LEXSenses>
            <LEXSense LanguageCode="en" LastEdited="2017-12-31 13:15:24" LastEditedBy="">
              <DefinitionLong/>
              <DefinitionShort>= indirect male progenitor</DefinitionShort>
              <Glosses>
                <Gloss>grandfather</Gloss>
                <Gloss>ancestor</Gloss>
              </Glosses>
              <Comments/>
            </LEXSense>
          </LEXSenses>
          <LEXReferences>
            <LEXReference>00100901800036</LEXReference>
            <LEXReference>00100902200008</LEXReference>
            <LEXReference>00101002100014</LEXReference>
            <LEXReference>00101501500010</LEXReference>
            <LEXReference>00101700400016</LEXReference>
            <LEXReference>00101700500026</LEXReference>
            <LEXReference>00101903700022</LEXReference>
            <LEXReference>00101903800026</LEXReference>
            <LEXReference>00102202100022</LEXReference>
            <LEXReference>00102801300024</LEXReference>
            <LEXReference>00103100300018</LEXReference>
            <LEXReference>00103201000010</LEXReference>
            <LEXReference>00103600900010</LEXReference>
            <LEXReference>00103604300030</LEXReference>
            <LEXReference>00104603400030</LEXReference>
            <LEXReference>00104700300036</LEXReference>
            <LEXReference>00104700900054</LEXReference>
            <LEXReference>00104703000008</LEXReference>
            <LEXReference>00104801500022</LEXReference>
            <LEXReference>00104802100036</LEXReference>
            <LEXReference>00104902900028</LEXReference>
            <LEXReference>00200300600010</LEXReference>
            <LEXReference>00200301300034</LEXReference>
            <LEXReference>00200301500028</LEXReference>
            <LEXReference>00200301600024</LEXReference>
            <LEXReference>00200400500016</LEXReference>
            <LEXReference>00201300500050</LEXReference>
            <LEXReference>00201301100032</LEXReference>
            <LEXReference>00201500200030</LEXReference>
            <LEXReference>00302504100032</LEXReference>
            <LEXReference>00302603900030</LEXReference>
            <LEXReference>00302604000016</LEXReference>
            <LEXReference>00401101200066</LEXReference>
            <LEXReference>00401402300018</LEXReference>
            <LEXReference>00401800200016</LEXReference>
            <LEXReference>00402001500006</LEXReference>
            <LEXReference>00402001500034</LEXReference>
            <LEXReference>00403200800006</LEXReference>
            <LEXReference>00403600300034</LEXReference>
            <LEXReference>00403600800050</LEXReference>
            <LEXReference>00500100800036</LEXReference>
            <LEXReference>00500101100006</LEXReference>
            <LEXReference>00500102100034</LEXReference>
            <LEXReference>00500103500050</LEXReference>
            <LEXReference>00500400100060</LEXReference>
            <LEXReference>00500403100032</LEXReference>
            <LEXReference>00500403700012</LEXReference>
            <LEXReference>00500500300006</LEXReference>
            <LEXReference>00500600300040</LEXReference>
            <LEXReference>00500601000026</LEXReference>
            <LEXReference>00500601800054</LEXReference>
            <LEXReference>00500602300036</LEXReference>
            <LEXReference>00500700800030</LEXReference>
            <LEXReference>00500701200060</LEXReference>
            <LEXReference>00500701300060</LEXReference>
            <LEXReference>00500800100054</LEXReference>
            <LEXReference>00500800300032</LEXReference>
            <LEXReference>00500801600020</LEXReference>
            <LEXReference>00500801800044</LEXReference>
            <LEXReference>00500900500072</LEXReference>
            <LEXReference>00501001100046</LEXReference>
            <LEXReference>00501001500006</LEXReference>
            <LEXReference>00501002200010</LEXReference>
            <LEXReference>00501100900024</LEXReference>
            <LEXReference>00501102100028</LEXReference>
            <LEXReference>00501200100036</LEXReference>
            <LEXReference>00501300700066</LEXReference>
            <LEXReference>00501301800056</LEXReference>
            <LEXReference>00501900800024</LEXReference>
            <LEXReference>00501900800050</LEXReference>
            <LEXReference>00502600300062</LEXReference>
            <LEXReference>00502600500022</LEXReference>
            <LEXReference>00502600700012</LEXReference>
            <LEXReference>00502601500050</LEXReference>
            <LEXReference>00502700300068</LEXReference>
            <LEXReference>00502801100048</LEXReference>
            <LEXReference>00502803600034</LEXReference>
            <LEXReference>00502806400054</LEXReference>
            <LEXReference>00502901200048</LEXReference>
            <LEXReference>00502902400020</LEXReference>
            <LEXReference>00503000500020</LEXReference>
            <LEXReference>00503000500036</LEXReference>
            <LEXReference>00503000900068</LEXReference>
            <LEXReference>00503002000058</LEXReference>
            <LEXReference>00503100700062</LEXReference>
            <LEXReference>00503101600018</LEXReference>
            <LEXReference>00503102000018</LEXReference>
            <LEXReference>00503201700032</LEXReference>
            <LEXReference>00600100600036</LEXReference>
            <LEXReference>00600500600084</LEXReference>
            <LEXReference>00601700100032</LEXReference>
            <LEXReference>00601800300046</LEXReference>
            <LEXReference>00601904700076</LEXReference>
            <LEXReference>00602104300030</LEXReference>
            <LEXReference>00602104400024</LEXReference>
            <LEXReference>00602202800042</LEXReference>
            <LEXReference>00602400200036</LEXReference>
            <LEXReference>00602400300008</LEXReference>
            <LEXReference>00602400600008</LEXReference>
            <LEXReference>00602400600030</LEXReference>
            <LEXReference>00602401400040</LEXReference>
            <LEXReference>00602401500044</LEXReference>
            <LEXReference>00602401700020</LEXReference>
            <LEXReference>00700200100052</LEXReference>
            <LEXReference>00700201000020</LEXReference>
            <LEXReference>00700201200012</LEXReference>
            <LEXReference>00700201700044</LEXReference>
            <LEXReference>00700201900022</LEXReference>
            <LEXReference>00700202000042</LEXReference>
            <LEXReference>00700202200036</LEXReference>
            <LEXReference>00700300400036</LEXReference>
            <LEXReference>00700601300046</LEXReference>
            <LEXReference>00701802900020</LEXReference>
            <LEXReference>00901200600038</LEXReference>
            <LEXReference>00901200700038</LEXReference>
            <LEXReference>00901200800016</LEXReference>
            <LEXReference>00901200800044</LEXReference>
            <LEXReference>00901201500040{N:001}</LEXReference>
            <LEXReference>01000701200014</LEXReference>
            <LEXReference>01001600300058</LEXReference>
            <LEXReference>01100102100018</LEXReference>
            <LEXReference>01100201000010</LEXReference>
            <LEXReference>01100802100030</LEXReference>
            <LEXReference>01100803400040</LEXReference>
            <LEXReference>01100804000032</LEXReference>
            <LEXReference>01100804800050</LEXReference>
            <LEXReference>01100805300044</LEXReference>
            <LEXReference>01100805700018</LEXReference>
            <LEXReference>01100805800042</LEXReference>
            <LEXReference>01100900900024</LEXReference>
            <LEXReference>01101102100020</LEXReference>
            <LEXReference>01101104300010</LEXReference>
            <LEXReference>01101302200054</LEXReference>
            <LEXReference>01101401500058</LEXReference>
            <LEXReference>01101402000028</LEXReference>
            <LEXReference>01101402200032</LEXReference>
            <LEXReference>01101403100010</LEXReference>
            <LEXReference>01101403100018</LEXReference>
            <LEXReference>01101500300044</LEXReference>
            <LEXReference>01101500800010</LEXReference>
            <LEXReference>01101501100022</LEXReference>
            <LEXReference>01101501200032</LEXReference>
            <LEXReference>01101502400010</LEXReference>
            <LEXReference>01101502400018</LEXReference>
            <LEXReference>01101502400026</LEXReference>
            <LEXReference>01101502600024</LEXReference>
            <LEXReference>01101600600010</LEXReference>
            <LEXReference>01101602800010</LEXReference>
            <LEXReference>01101900400070</LEXReference>
            <LEXReference>01102100300028</LEXReference>
            <LEXReference>01102100400050</LEXReference>
            <LEXReference>01102204000010</LEXReference>
            <LEXReference>01102205100010</LEXReference>
            <LEXReference>01102205100018</LEXReference>
            <LEXReference>01102205100026</LEXReference>
            <LEXReference>01200802400010</LEXReference>
            <LEXReference>01200802400018</LEXReference>
            <LEXReference>01200902800024</LEXReference>
            <LEXReference>01201003500010</LEXReference>
            <LEXReference>01201201900034</LEXReference>
            <LEXReference>01201202200034</LEXReference>
            <LEXReference>01201300900010</LEXReference>
            <LEXReference>01201301300010</LEXReference>
            <LEXReference>01201400300024</LEXReference>
            <LEXReference>01201401600010</LEXReference>
            <LEXReference>01201402000024</LEXReference>
            <LEXReference>01201402200028</LEXReference>
            <LEXReference>01201402900010</LEXReference>
            <LEXReference>01201500700010</LEXReference>
            <LEXReference>01201500700020</LEXReference>
            <LEXReference>01201500900022</LEXReference>
            <LEXReference>01201502200010</LEXReference>
            <LEXReference>01201503800010</LEXReference>
            <LEXReference>01201503800018</LEXReference>
            <LEXReference>01201503800026</LEXReference>
            <LEXReference>01201600200050</LEXReference>
            <LEXReference>01201602000010</LEXReference>
            <LEXReference>01201602000018</LEXReference>
            <LEXReference>01201701300068</LEXReference>
            <LEXReference>01201701400020</LEXReference>
            <LEXReference>01201701500022</LEXReference>
            <LEXReference>01201704100046</LEXReference>
            <LEXReference>01201800300026</LEXReference>
            <LEXReference>01201901200018</LEXReference>
            <LEXReference>01202000500026</LEXReference>
            <LEXReference>01202001700026</LEXReference>
            <LEXReference>01202002100010</LEXReference>
            <LEXReference>01202100800028</LEXReference>
            <LEXReference>01202101500036</LEXReference>
            <LEXReference>01202101800010</LEXReference>
            <LEXReference>01202102200012</LEXReference>
            <LEXReference>01202200200028</LEXReference>
            <LEXReference>01202201300068</LEXReference>
            <LEXReference>01202202000010</LEXReference>
            <LEXReference>01202303200024</LEXReference>
            <LEXReference>01202303700024</LEXReference>
            <LEXReference>01202400600010</LEXReference>
            <LEXReference>01300205500034</LEXReference>
            <LEXReference>01300502500010</LEXReference>
            <LEXReference>01300901900054</LEXReference>
            <LEXReference>01301201800074</LEXReference>
            <LEXReference>01301701100018</LEXReference>
            <LEXReference>01302401900030</LEXReference>
            <LEXReference>01302901000038</LEXReference>
            <LEXReference>01302901500020</LEXReference>
            <LEXReference>01302901800014</LEXReference>
            <LEXReference>01302902000042</LEXReference>
            <LEXReference>01400602500046</LEXReference>
            <LEXReference>01400603100040</LEXReference>
            <LEXReference>01400603800048</LEXReference>
            <LEXReference>01400702200018</LEXReference>
            <LEXReference>01400903100010</LEXReference>
            <LEXReference>01401101600048</LEXReference>
            <LEXReference>01401201600010</LEXReference>
            <LEXReference>01401301200050</LEXReference>
            <LEXReference>01401301800038</LEXReference>
            <LEXReference>01401302300010</LEXReference>
            <LEXReference>01401400300020</LEXReference>
            <LEXReference>01401501200022</LEXReference>
            <LEXReference>01401601300010</LEXReference>
            <LEXReference>01401900400048</LEXReference>
            <LEXReference>01402000600010</LEXReference>
            <LEXReference>01402003300030</LEXReference>
            <LEXReference>01402100100010</LEXReference>
            <LEXReference>01402100100018</LEXReference>
            <LEXReference>01402101000058</LEXReference>
            <LEXReference>01402101200032</LEXReference>
            <LEXReference>01402101900066</LEXReference>
            <LEXReference>01402401800014</LEXReference>
            <LEXReference>01402402400044</LEXReference>
            <LEXReference>01402502800020</LEXReference>
            <LEXReference>01402600200028</LEXReference>
            <LEXReference>01402602300010</LEXReference>
            <LEXReference>01402602300020</LEXReference>
            <LEXReference>01402700900010</LEXReference>
            <LEXReference>01402800100048</LEXReference>
            <LEXReference>01402800600048</LEXReference>
            <LEXReference>01402800900054</LEXReference>
            <LEXReference>01402802500042</LEXReference>
            <LEXReference>01402802700010</LEXReference>
            <LEXReference>01402900200026</LEXReference>
            <LEXReference>01402900500030</LEXReference>
            <LEXReference>01402900600006</LEXReference>
            <LEXReference>01402900900008</LEXReference>
            <LEXReference>01403000700010</LEXReference>
            <LEXReference>01403000700028</LEXReference>
            <LEXReference>01403000800012</LEXReference>
            <LEXReference>01403001900020</LEXReference>
            <LEXReference>01403002200062</LEXReference>
            <LEXReference>01403201300016</LEXReference>
            <LEXReference>01403201400022</LEXReference>
            <LEXReference>01403201500068</LEXReference>
            <LEXReference>01403203300010</LEXReference>
            <LEXReference>01403300800032</LEXReference>
            <LEXReference>01403301200034</LEXReference>
            <LEXReference>01403302000010</LEXReference>
            <LEXReference>01403400200026</LEXReference>
            <LEXReference>01403400300034</LEXReference>
            <LEXReference>01403402100064</LEXReference>
            <LEXReference>01403402800008</LEXReference>
            <LEXReference>01403403200038</LEXReference>
            <LEXReference>01403403300074</LEXReference>
            <LEXReference>01403502400048</LEXReference>
            <LEXReference>01403601500010</LEXReference>
            <LEXReference>01500702700008</LEXReference>
            <LEXReference>01500802800044</LEXReference>
            <LEXReference>01500900700006</LEXReference>
            <LEXReference>01501001100016</LEXReference>
            <LEXReference>01600200300040</LEXReference>
            <LEXReference>01600200500048</LEXReference>
            <LEXReference>01600900200034</LEXReference>
            <LEXReference>01600900900010</LEXReference>
            <LEXReference>01600901600008</LEXReference>
            <LEXReference>01600902300032</LEXReference>
            <LEXReference>01600903200082</LEXReference>
            <LEXReference>01600903400014</LEXReference>
            <LEXReference>01600903600024</LEXReference>
            <LEXReference>01601301800010</LEXReference>
            <LEXReference>01800800800022</LEXReference>
            <LEXReference>01801501800016</LEXReference>
            <LEXReference>01902200500006</LEXReference>
            <LEXReference>01903901300036</LEXReference>
            <LEXReference>01904400200010</LEXReference>
            <LEXReference>01904501700004</LEXReference>
            <LEXReference>01904902000008</LEXReference>
            <LEXReference>01907800300012</LEXReference>
            <LEXReference>01907800500028</LEXReference>
            <LEXReference>01907800800010</LEXReference>
            <LEXReference>01907801200004</LEXReference>
            <LEXReference>01907805700012</LEXReference>
            <LEXReference>01909500900006</LEXReference>
            <LEXReference>01910600600006</LEXReference>
            <LEXReference>01910600700002</LEXReference>
            <LEXReference>01910901400006</LEXReference>
            <LEXReference>02001901400010</LEXReference>
            <LEXReference>02002202800014</LEXReference>
            <LEXReference>02301402100014</LEXReference>
            <LEXReference>02303701200018</LEXReference>
            <LEXReference>02303800500022</LEXReference>
            <LEXReference>02303900600026</LEXReference>
            <LEXReference>02304302700002</LEXReference>
            <LEXReference>02305100200008</LEXReference>
            <LEXReference>02305801400030</LEXReference>
            <LEXReference>02306401000014</LEXReference>
            <LEXReference>02306500700008</LEXReference>
            <LEXReference>02400200500012</LEXReference>
            <LEXReference>02400301800048</LEXReference>
            <LEXReference>02400302400014</LEXReference>
            <LEXReference>02400302500028</LEXReference>
            <LEXReference>02400700700030</LEXReference>
            <LEXReference>02400701400046</LEXReference>
            <LEXReference>02400702200010</LEXReference>
            <LEXReference>02400702500014</LEXReference>
            <LEXReference>02400702600032</LEXReference>
            <LEXReference>02400901300024</LEXReference>
            <LEXReference>02400901500022</LEXReference>
            <LEXReference>02401100400008</LEXReference>
            <LEXReference>02401100500018</LEXReference>
            <LEXReference>02401100700010</LEXReference>
            <LEXReference>02401101000008</LEXReference>
            <LEXReference>02401101000064</LEXReference>
            <LEXReference>02401402000010</LEXReference>
            <LEXReference>02401601100014</LEXReference>
            <LEXReference>02401601200014</LEXReference>
            <LEXReference>02401601300036</LEXReference>
            <LEXReference>02401601500056</LEXReference>
            <LEXReference>02401601900042</LEXReference>
            <LEXReference>02401702200052</LEXReference>
            <LEXReference>02401900400044</LEXReference>
            <LEXReference>02402302700036</LEXReference>
            <LEXReference>02402303900038</LEXReference>
            <LEXReference>02402401000050</LEXReference>
            <LEXReference>02402500500050</LEXReference>
            <LEXReference>02403000300050</LEXReference>
            <LEXReference>02403103200016</LEXReference>
            <LEXReference>02403202200024</LEXReference>
            <LEXReference>02403400500014</LEXReference>
            <LEXReference>02403401300020</LEXReference>
            <LEXReference>02403401400052</LEXReference>
            <LEXReference>02403500600020</LEXReference>
            <LEXReference>02403500800016</LEXReference>
            <LEXReference>02403501000030</LEXReference>
            <LEXReference>02403501400054</LEXReference>
            <LEXReference>02403501500084</LEXReference>
            <LEXReference>02403501600018</LEXReference>
            <LEXReference>02403501800040</LEXReference>
            <LEXReference>02404400300046</LEXReference>
            <LEXReference>02404400900010</LEXReference>
            <LEXReference>02404401000052</LEXReference>
            <LEXReference>02404401700054</LEXReference>
            <LEXReference>02404402100034</LEXReference>
            <LEXReference>02405000700036</LEXReference>
            <LEXReference>02500500700002</LEXReference>
            <LEXReference>02600200300042</LEXReference>
            <LEXReference>02601600300032</LEXReference>
            <LEXReference>02601604500040</LEXReference>
            <LEXReference>02602000400020</LEXReference>
            <LEXReference>02602001800020</LEXReference>
            <LEXReference>02602002400030</LEXReference>
            <LEXReference>02602002700038</LEXReference>
            <LEXReference>02602003000026</LEXReference>
            <LEXReference>02602003600010</LEXReference>
            <LEXReference>02602004200046</LEXReference>
            <LEXReference>02603602800018</LEXReference>
            <LEXReference>02603702500030</LEXReference>
            <LEXReference>02604701400028</LEXReference>
            <LEXReference>02700900600032</LEXReference>
            <LEXReference>02700900800024</LEXReference>
            <LEXReference>02700901600042</LEXReference>
            <LEXReference>02701102400026</LEXReference>
            <LEXReference>02701102400030</LEXReference>
            <LEXReference>02701102400032</LEXReference>
            <LEXReference>02701103700008</LEXReference>
            <LEXReference>02701103800028</LEXReference>
            <LEXReference>02800901000030</LEXReference>
            <LEXReference>02900100200040</LEXReference>
            <LEXReference>03000200400054</LEXReference>
            <LEXReference>03300702000022</LEXReference>
            <LEXReference>03800100200008</LEXReference>
            <LEXReference>03800100400008</LEXReference>
            <LEXReference>03800100500002</LEXReference>
            <LEXReference>03800100600028</LEXReference>
            <LEXReference>03800801400028</LEXReference>
            <LEXReference>03900201000040</LEXReference>
            <LEXReference>03900300700008</LEXReference>
          </LEXReferences>
          <LEXVideos/>
          <LEXCoreDomains>
            <LEXCoreDomain Code="129">Posterity</LEXCoreDomain>
          </LEXCoreDomains>
        </LEXMeaning>
        <LEXMeaning Id="000003001003000" IsBiblicalTerm="M" EntryCode="" Indent="0">
          <LEXDomains>
            <LEXDomain Code="001001002003012">Relatives</LEXDomain>
          </LEXDomains>
          <LEXSenses>
            <LEXSense LanguageCode="en" LastEdited="2017-12-31 13:15:24" LastEditedBy="">
              <DefinitionLong/>
              <DefinitionShort>= a person ► who is the founder of a village, town, or region, and usually the ancestor of most of its inhabitants</DefinitionShort>
              <Glosses>
                <Gloss>father &gt; founder</Gloss>
              </Glosses>
              <Comments/>
            </LEXSense>
          </LEXSenses>
          <LEXReferences>
            <LEXReference>00103301900030</LEXReference>
            <LEXReference>00602403200050</LEXReference>
            <LEXReference>00700902800048</LEXReference>
            <LEXReference>01300202100016</LEXReference>
            <LEXReference>01300202300044</LEXReference>
            <LEXReference>01300202400034</LEXReference>
            <LEXReference>01300204200018</LEXReference>
            <LEXReference>01300204200028</LEXReference>
            <LEXReference>01300204500014</LEXReference>
            <LEXReference>01300204900008</LEXReference>
            <LEXReference>01300204900016</LEXReference>
            <LEXReference>01300204900022</LEXReference>
            <LEXReference>01300205000020</LEXReference>
            <LEXReference>01300205100004</LEXReference>
            <LEXReference>01300205100010</LEXReference>
            <LEXReference>01300205200012</LEXReference>
            <LEXReference>01300400300006{N:002}</LEXReference>
            <LEXReference>01300400400006</LEXReference>
            <LEXReference>01300400400014</LEXReference>
            <LEXReference>01300400400028</LEXReference>
            <LEXReference>01300400500008</LEXReference>
            <LEXReference>01300401100018</LEXReference>
            <LEXReference>01300401200026</LEXReference>
            <LEXReference>01300401400022</LEXReference>
            <LEXReference>01300401800016</LEXReference>
            <LEXReference>01300401800026</LEXReference>
            <LEXReference>01300401800036</LEXReference>
            <LEXReference>01300402100012</LEXReference>
            <LEXReference>01300402100020</LEXReference>
            <LEXReference>01300701400024</LEXReference>
            <LEXReference>01300703100016</LEXReference>
            <LEXReference>01300802900010</LEXReference>
            <LEXReference>01300903500010</LEXReference>
          </LEXReferences>
          <LEXVideos/>
          <LEXCoreDomains>
            <LEXCoreDomain Code="182">Town</LEXCoreDomain>
          </LEXCoreDomains>
        </LEXMeaning>
        <LEXMeaning Id="000003001004000" IsBiblicalTerm="M" EntryCode="" Indent="0">
          <LEXDomains>
            <LEXDomain Code="002003003010" Source="Relatives" SourceCode="001001002003012">Engage</LEXDomain>
          </LEXDomains>
          <LEXSenses>
            <LEXSense LanguageCode="en" LastEdited="2017-12-31 13:15:24" LastEditedBy="">
              <DefinitionLong/>
              <DefinitionShort>= a person ► who is the first to be engaged in a certain activity or pattern of behavior</DefinitionShort>
              <Glosses>
                <Gloss>the first person to ...</Gloss>
              </Glosses>
              <Comments/>
            </LEXSense>
          </LEXSenses>
          <LEXReferences>
            <LEXReference>00100402000016</LEXReference>
            <LEXReference>00100402100014</LEXReference>
          </LEXReferences>
          <LEXVideos/>
        </LEXMeaning>
        <LEXMeaning Id="000003001005000" IsBiblicalTerm="M" EntryCode="" Indent="0">
          <LEXDomains>
            <LEXDomain Code="002002002005" Source="Relatives" SourceCode="001001002003012">Exist</LEXDomain>
          </LEXDomains>
          <LEXSenses>
            <LEXSense LanguageCode="en" LastEdited="2017-12-31 13:15:24" LastEditedBy="">
              <DefinitionLong/>
              <DefinitionShort>= a person, ◄ compared to a father, ► who is the originator of a certain process; ≈ said about God only</DefinitionShort>
              <Glosses>
                <Gloss>father &gt; creator</Gloss>
              </Glosses>
              <Comments/>
            </LEXSense>
          </LEXSenses>
          <LEXReferences>
            <LEXReference>00503200600028</LEXReference>
            <LEXReference>01803802800012</LEXReference>
            <LEXReference>02400202700010</LEXReference>
            <LEXReference>03900201000006</LEXReference>
          </LEXReferences>
          <LEXVideos/>
          <LEXCoreDomains>
            <LEXCoreDomain Code="028">Creation</LEXCoreDomain>
          </LEXCoreDomains>
        </LEXMeaning>
        <LEXMeaning Id="000003001006000" IsBiblicalTerm="M" EntryCode="" Indent="0">
          <LEXDomains>
            <LEXDomain Code="001001002003007" Source="Relatives" SourceCode="001001002003012">Officials</LEXDomain>
          </LEXDomains>
          <LEXSenses>
            <LEXSense LanguageCode="en" LastEdited="2017-12-31 13:15:24" LastEditedBy="">
              <DefinitionLong/>
              <DefinitionShort>= a person, ◄ compared to a father, ► who provides advice to someone in authority</DefinitionShort>
              <Glosses>
                <Gloss>adviser</Gloss>
              </Glosses>
              <Comments/>
            </LEXSense>
          </LEXSenses>
          <LEXReferences>
            <LEXReference>00104500800028</LEXReference>
            <LEXReference>00701701000022</LEXReference>
            <LEXReference>00701801900032</LEXReference>
          </LEXReferences>
          <LEXVideos/>
          <LEXCoreDomains>
            <LEXCoreDomain Code="199">Wisdom</LEXCoreDomain>
          </LEXCoreDomains>
        </LEXMeaning>
        <LEXMeaning Id="000003001007000" IsBiblicalTerm="M" EntryCode="" Indent="0">
          <LEXDomains>
            <LEXDomain Code="002003003018" Source="Relatives" SourceCode="001001002003012">Safe</LEXDomain>
          </LEXDomains>
          <LEXSenses>
            <LEXSense LanguageCode="en" LastEdited="2017-12-31 13:15:24" LastEditedBy="">
              <DefinitionLong/>
              <DefinitionShort>= a person, ◄ compared to a father, ► who provides care for the people under his authority; ≈ often extended to refer to God</DefinitionShort>
              <Glosses>
                <Gloss>father</Gloss>
                <Gloss>protector</Gloss>
                <Gloss>helper</Gloss>
              </Glosses>
              <Comments/>
            </LEXSense>
          </LEXSenses>
          <LEXReferences>
            <LEXReference>01000701400010</LEXReference>
            <LEXReference>01301701300010</LEXReference>
            <LEXReference>01302201000032</LEXReference>
            <LEXReference>01302800600044</LEXReference>
            <LEXReference>01802901600002</LEXReference>
            <LEXReference>01906800600002</LEXReference>
            <LEXReference>01908902700006</LEXReference>
            <LEXReference>02300900500042</LEXReference>
            <LEXReference>02302202100030</LEXReference>
            <LEXReference>02306301600006</LEXReference>
            <LEXReference>02306301600028</LEXReference>
            <LEXReference>02306400700008</LEXReference>
            <LEXReference>02400300400016</LEXReference>
            <LEXReference>02400301900040</LEXReference>
            <LEXReference>02403100900046</LEXReference>
            <LEXReference>03900100600018</LEXReference>
          </LEXReferences>
          <LEXVideos/>
          <LEXCoreDomains>
            <LEXCoreDomain Code="196">Well-Being</LEXCoreDomain>
          </LEXCoreDomains>
        </LEXMeaning>
        <LEXMeaning Id="000003001008000" IsBiblicalTerm="M" EntryCode="" Indent="0">
          <LEXDomains>
            <LEXDomain Code="001005001009" Source="Relatives" SourceCode="001001002003012">Tombs</LEXDomain>
          </LEXDomains>
          <LEXSenses>
            <LEXSense LanguageCode="en" LastEdited="2017-12-31 13:15:24" LastEditedBy="">
              <DefinitionLong/>
              <DefinitionShort>= a location, ◄ compared to a father, ≈ regarded as a source of security and comfort</DefinitionShort>
              <Glosses>
                <Gloss>father</Gloss>
                <Gloss>place of security</Gloss>
                <Gloss>place of comfort</Gloss>
              </Glosses>
              <Comments/>
            </LEXSense>
          </LEXSenses>
          <LEXReferences>
            <LEXReference>01801701400010</LEXReference>
          </LEXReferences>
          <LEXVideos/>
          <LEXCoreDomains>
            <LEXCoreDomain Code="196">Well-Being</LEXCoreDomain>
            <LEXCoreDomain Code="099">Life and Death</LEXCoreDomain>
          </LEXCoreDomains>
        </LEXMeaning>
        <LEXMeaning Id="000003001009000" IsBiblicalTerm="M" EntryCode="" Indent="0">
          <LEXDomains>
            <LEXDomain Code="001001002003004">Groups</LEXDomain>
          </LEXDomains>
          <LEXCollocations>
            <LEXCollocation>בֵּית־אָב</LEXCollocation>
          </LEXCollocations>
          <LEXSenses>
            <LEXSense LanguageCode="en" LastEdited="2017-12-31 13:15:24" LastEditedBy="">
              <DefinitionLong/>
              <DefinitionShort>= a group of people to which one traces one's ancestry; ◄ smallest unit within family group</DefinitionShort>
              <Glosses>
                <Gloss>father's house = family</Gloss>
              </Glosses>
              <Comments/>
            </LEXSense>
          </LEXSenses>
          <LEXReferences>
            <LEXReference>00101200100032</LEXReference>
            <LEXReference>00102001300020</LEXReference>
            <LEXReference>00102400700018</LEXReference>
            <LEXReference>00102402300024</LEXReference>
            <LEXReference>00102403800010</LEXReference>
            <LEXReference>00102404000050</LEXReference>
            <LEXReference>00102802100014</LEXReference>
            <LEXReference>00103101400034</LEXReference>
            <LEXReference>00103103000020</LEXReference>
            <LEXReference>00103401900042</LEXReference>
            <LEXReference>00103801100020</LEXReference>
            <LEXReference>00103801100058</LEXReference>
            <LEXReference>00104105100038</LEXReference>
            <LEXReference>00104603100018</LEXReference>
            <LEXReference>00104603100042</LEXReference>
            <LEXReference>00104701200026</LEXReference>
            <LEXReference>00105000800018</LEXReference>
            <LEXReference>00105002200018</LEXReference>
            <LEXReference>00200601400008</LEXReference>
            <LEXReference>00201200300046</LEXReference>
            <LEXReference>00302201300034</LEXReference>
            <LEXReference>00400100200024</LEXReference>
            <LEXReference>00400100400026</LEXReference>
            <LEXReference>00400101800040</LEXReference>
            <LEXReference>00400102000024</LEXReference>
            <LEXReference>00400102200018</LEXReference>
            <LEXReference>00400102400018</LEXReference>
            <LEXReference>00400102600018</LEXReference>
            <LEXReference>00400102800018</LEXReference>
            <LEXReference>00400103000018</LEXReference>
            <LEXReference>00400103200024</LEXReference>
            <LEXReference>00400103400018</LEXReference>
            <LEXReference>00400103600018</LEXReference>
            <LEXReference>00400103800018</LEXReference>
            <LEXReference>00400104000018</LEXReference>
            <LEXReference>00400104200016</LEXReference>
            <LEXReference>00400104400038</LEXReference>
            <LEXReference>00400104500018</LEXReference>
            <LEXReference>00400200200016</LEXReference>
            <LEXReference>00400203200014</LEXReference>
            <LEXReference>00400203400048</LEXReference>
            <LEXReference>00400301500014</LEXReference>
            <LEXReference>00400302000032</LEXReference>
            <LEXReference>00400302400008</LEXReference>
            <LEXReference>00400303000008</LEXReference>
            <LEXReference>00400303500008</LEXReference>
            <LEXReference>00400400200028</LEXReference>
            <LEXReference>00400402200020</LEXReference>
            <LEXReference>00400402900014</LEXReference>
            <LEXReference>00400403400038</LEXReference>
            <LEXReference>00400403800020</LEXReference>
            <LEXReference>00400404000016</LEXReference>
            <LEXReference>00400404200020</LEXReference>
            <LEXReference>00400404600040</LEXReference>
            <LEXReference>00400700200014</LEXReference>
            <LEXReference>00401701700026</LEXReference>
            <LEXReference>00401701700040</LEXReference>
            <LEXReference>00401701800030</LEXReference>
            <LEXReference>00401702100044</LEXReference>
            <LEXReference>00401800100022</LEXReference>
            <LEXReference>00402501400034</LEXReference>
            <LEXReference>00402501500030</LEXReference>
            <LEXReference>00402600200032</LEXReference>
            <LEXReference>00403000400026</LEXReference>
            <LEXReference>00403001700040</LEXReference>
            <LEXReference>00403401400018</LEXReference>
            <LEXReference>00403401400034</LEXReference>
            <LEXReference>00600201200036</LEXReference>
            <LEXReference>00600201800068</LEXReference>
            <LEXReference>00600602500018</LEXReference>
            <LEXReference>00602201400022</LEXReference>
            <LEXReference>00602201400040</LEXReference>
            <LEXReference>00700601500046</LEXReference>
            <LEXReference>00700602700044</LEXReference>
            <LEXReference>00700900100036</LEXReference>
            <LEXReference>00700901800012</LEXReference>
            <LEXReference>00701100200046</LEXReference>
            <LEXReference>00701100700032</LEXReference>
            <LEXReference>00701401500056</LEXReference>
            <LEXReference>00701603100014</LEXReference>
            <LEXReference>00701900200022</LEXReference>
            <LEXReference>00900202700036</LEXReference>
            <LEXReference>00900202800054</LEXReference>
            <LEXReference>00900203000022</LEXReference>
            <LEXReference>00900203100024</LEXReference>
            <LEXReference>00900902000066</LEXReference>
            <LEXReference>00901702500076</LEXReference>
            <LEXReference>00901800200030</LEXReference>
            <LEXReference>00902200100034</LEXReference>
            <LEXReference>00902201100034</LEXReference>
            <LEXReference>00902201600024</LEXReference>
            <LEXReference>00902202200058</LEXReference>
            <LEXReference>00902402200038</LEXReference>
            <LEXReference>01000302900018</LEXReference>
            <LEXReference>01001400900038</LEXReference>
            <LEXReference>01001902900012</LEXReference>
            <LEXReference>01002401700074</LEXReference>
            <LEXReference>01100203100056</LEXReference>
            <LEXReference>01101801800024</LEXReference>
            <LEXReference>01300403800022</LEXReference>
            <LEXReference>01300501300010</LEXReference>
            <LEXReference>01300501500018</LEXReference>
            <LEXReference>01300502400010</LEXReference>
            <LEXReference>01300502400056</LEXReference>
            <LEXReference>01300700200036</LEXReference>
            <LEXReference>01300700400014</LEXReference>
            <LEXReference>01300700700032</LEXReference>
            <LEXReference>01300700900014</LEXReference>
            <LEXReference>01300704000016</LEXReference>
            <LEXReference>01300900900036</LEXReference>
            <LEXReference>01300901300012</LEXReference>
            <LEXReference>01300901900026</LEXReference>
            <LEXReference>01301202900016</LEXReference>
            <LEXReference>01301203100032</LEXReference>
            <LEXReference>01302101700078</LEXReference>
            <LEXReference>01302301100042</LEXReference>
            <LEXReference>01302302400012</LEXReference>
            <LEXReference>01302400400042</LEXReference>
            <LEXReference>01302400400060</LEXReference>
            <LEXReference>01302400600076</LEXReference>
            <LEXReference>01302403000030</LEXReference>
            <LEXReference>01302600600022</LEXReference>
            <LEXReference>01302601300024</LEXReference>
            <LEXReference>01302800400020</LEXReference>
            <LEXReference>01302800400060</LEXReference>
            <LEXReference>01401701400012</LEXReference>
            <LEXReference>01402101300048</LEXReference>
            <LEXReference>01402500500020</LEXReference>
            <LEXReference>01403101700016</LEXReference>
            <LEXReference>01403500400014</LEXReference>
            <LEXReference>01403500500020</LEXReference>
            <LEXReference>01403500500038</LEXReference>
            <LEXReference>01403501200022</LEXReference>
            <LEXReference>01500205900034</LEXReference>
            <LEXReference>01501001600036</LEXReference>
            <LEXReference>01600100600080</LEXReference>
            <LEXReference>01600706100036</LEXReference>
            <LEXReference>01601003500046</LEXReference>
            <LEXReference>01700401400048</LEXReference>
            <LEXReference>01904501100026</LEXReference>
            <LEXReference>02300300600014</LEXReference>
            <LEXReference>02300701700020</LEXReference>
            <LEXReference>02302202300028</LEXReference>
            <LEXReference>02302202400014</LEXReference>
            <LEXReference>02401200600012</LEXReference>
          </LEXReferences>
          <LEXVideos/>
          <LEXCoreDomains>
            <LEXCoreDomain Code="062">Family</LEXCoreDomain>
          </LEXCoreDomains>
        </LEXMeaning>
        <LEXMeaning Id="000003001010000" IsBiblicalTerm="M" EntryCode="" Indent="0">
          <LEXDomains>
            <LEXDomain Code="001001002003004">Groups</LEXDomain>
          </LEXDomains>
          <LEXCollocations>
            <LEXCollocation>מַטֵּה אֲבֹות</LEXCollocation>
          </LEXCollocations>
          <LEXSenses>
            <LEXSense LanguageCode="en" LastEdited="2017-12-31 13:15:24" LastEditedBy="">
              <DefinitionLong/>
              <DefinitionShort>= a group of people to which one traces one's ancestry; ◄ largest unit within family group</DefinitionShort>
              <Glosses>
                <Gloss>ancestral tribe</Gloss>
              </Glosses>
              <Comments/>
            </LEXSense>
          </LEXSenses>
          <LEXReferences>
            <LEXReference>00400101600016</LEXReference>
            <LEXReference>00400104700012</LEXReference>
            <LEXReference>00401300200042</LEXReference>
            <LEXReference>00402605500022</LEXReference>
            <LEXReference>00403305400068</LEXReference>
            <LEXReference>00403600400046</LEXReference>
            <LEXReference>00403600600048</LEXReference>
            <LEXReference>00403600700034</LEXReference>
            <LEXReference>00403600800030</LEXReference>
          </LEXReferences>
          <LEXVideos/>
          <LEXCoreDomains>
            <LEXCoreDomain Code="062">Family</LEXCoreDomain>
          </LEXCoreDomains>
        </LEXMeaning>
        <LEXMeaning Id="000003001011000" IsBiblicalTerm="M" EntryCode="" Indent="0">
          <LEXDomains>
            <LEXDomain Code="001001002003004">Groups</LEXDomain>
          </LEXDomains>
          <LEXCollocations>
            <LEXCollocation>אָבֹות</LEXCollocation>
          </LEXCollocations>
          <LEXSenses>
            <LEXSense LanguageCode="en" LastEdited="2017-12-31 13:15:24" LastEditedBy="">
              <DefinitionLong/>
              <DefinitionShort>= a group of people to which one traces one's ancestry</DefinitionShort>
              <Glosses>
                <Gloss>ancestry</Gloss>
              </Glosses>
              <Comments/>
            </LEXSense>
          </LEXSenses>
          <LEXReferences>
            <LEXReference>00200602500040</LEXReference>
            <LEXReference>00403102600042</LEXReference>
            <LEXReference>00403202800034</LEXReference>
            <LEXReference>00403600100010</LEXReference>
            <LEXReference>00403600100058</LEXReference>
            <LEXReference>00601400100044</LEXReference>
            <LEXReference>00602100100008</LEXReference>
            <LEXReference>00602100100038</LEXReference>
            <LEXReference>01100800100028</LEXReference>
            <LEXReference>01300600400024</LEXReference>
            <LEXReference>01300701100016</LEXReference>
            <LEXReference>01300800600016</LEXReference>
            <LEXReference>01300801000026</LEXReference>
            <LEXReference>01300801300016</LEXReference>
            <LEXReference>01300802800006</LEXReference>
            <LEXReference>01300900900030</LEXReference>
            <LEXReference>01300903300012</LEXReference>
            <LEXReference>01300903400008</LEXReference>
            <LEXReference>01301501200014</LEXReference>
            <LEXReference>01302300900026</LEXReference>
            <LEXReference>01302302400018</LEXReference>
            <LEXReference>01302400600058</LEXReference>
            <LEXReference>01302403100046</LEXReference>
            <LEXReference>01302403100062</LEXReference>
            <LEXReference>01302602100020</LEXReference>
            <LEXReference>01302602600036</LEXReference>
            <LEXReference>01302603100026</LEXReference>
            <LEXReference>01302603200022</LEXReference>
            <LEXReference>01302700100016</LEXReference>
            <LEXReference>01302900600010</LEXReference>
            <LEXReference>01400100200054</LEXReference>
            <LEXReference>01400500200030</LEXReference>
            <LEXReference>01401900800034</LEXReference>
            <LEXReference>01402300200034</LEXReference>
            <LEXReference>01402601200010</LEXReference>
            <LEXReference>01500100500010</LEXReference>
            <LEXReference>01500206800010</LEXReference>
            <LEXReference>01500301200024</LEXReference>
            <LEXReference>01500400200018</LEXReference>
            <LEXReference>01500400300022</LEXReference>
            <LEXReference>01500800100008</LEXReference>
            <LEXReference>01500802900034</LEXReference>
            <LEXReference>01501001600030</LEXReference>
            <LEXReference>01600706900012</LEXReference>
            <LEXReference>01600707000010</LEXReference>
            <LEXReference>01600801300020</LEXReference>
            <LEXReference>01601101300010</LEXReference>
            <LEXReference>01601201200018</LEXReference>
            <LEXReference>01601202200026</LEXReference>
            <LEXReference>01601202300010</LEXReference>
          </LEXReferences>
          <LEXVideos/>
          <LEXCoreDomains>
            <LEXCoreDomain Code="062">Family</LEXCoreDomain>
          </LEXCoreDomains>
        </LEXMeaning>
        <LEXMeaning Id="000003001012000" IsBiblicalTerm="M" EntryCode="" Indent="0">
          <LEXDomains>
            <LEXDomain Code="002003002020" Source="Groups" SourceCode="001001002003004">Possess</LEXDomain>
          </LEXDomains>
          <LEXCollocations>
            <LEXCollocation>אָבֹות</LEXCollocation>
          </LEXCollocations>
          <LEXSenses>
            <LEXSense LanguageCode="en" LastEdited="2017-12-31 13:15:24" LastEditedBy="">
              <DefinitionLong/>
              <DefinitionShort>= possessions belonging to a group of people that share a common ancestry</DefinitionShort>
              <Glosses>
                <Gloss>family possessions</Gloss>
                <Gloss>patrimony</Gloss>
              </Glosses>
              <Comments/>
            </LEXSense>
          </LEXSenses>
          <LEXReferences>
            <LEXReference>00501800800020</LEXReference>
          </LEXReferences>
          <LEXVideos/>
          <LEXCoreDomains>
            <LEXCoreDomain Code="062">Family</LEXCoreDomain>
            <LEXCoreDomain Code="128">Possession</LEXCoreDomain>
          </LEXCoreDomains>
        </LEXMeaning>
        <LEXMeaning Id="000003001013000" IsBiblicalTerm="Y" EntryCode="" Indent="0">
          <LEXDomains>
            <LEXDomain Code="003001017">Titles</LEXDomain>
          </LEXDomains>
          <LEXSenses>
            <LEXSense LanguageCode="en" LastEdited="2017-12-31 13:15:24" LastEditedBy="">
              <DefinitionLong/>
              <DefinitionShort>= way of addressing a male person that one regards as one's superior because of his age, status, authority, etc.</DefinitionShort>
              <Glosses>
                <Gloss>father (as title)</Gloss>
              </Glosses>
              <Comments/>
            </LEXSense>
          </LEXSenses>
          <LEXReferences>
            <LEXReference>00902401200004</LEXReference>
            <LEXReference>01200201200014</LEXReference>
            <LEXReference>01200201200016</LEXReference>
            <LEXReference>01200501300018</LEXReference>
            <LEXReference>01200602100026</LEXReference>
            <LEXReference>01201301400042</LEXReference>
            <LEXReference>01201301400044</LEXReference>
          </LEXReferences>
          <LEXVideos/>
        </LEXMeaning>
        <LEXMeaning Id="000003001014000" IsBiblicalTerm="N" EntryCode="" Indent="0">
          <LEXSenses>
            <LEXSense LanguageCode="en" LastEdited="2017-12-31 13:15:24" LastEditedBy="">
              <DefinitionLong/>
              <DefinitionShort>see {L:אָבִי&lt;SDBH:אָבִי&gt;}</DefinitionShort>
              <Glosses>
                <Gloss>would that ...!</Gloss>
              </Glosses>
              <Comments/>
            </LEXSense>
          </LEXSenses>
          <LEXReferences>
            <LEXReference>01803403600002</LEXReference>
          </LEXReferences>
          <LEXVideos/>
        </LEXMeaning>
        <LEXMeaning Id="000003001015000" IsBiblicalTerm="N" EntryCode="" Indent="0">
          <LEXSenses>
            <LEXSense LanguageCode="en" LastEdited="2017-12-31 13:15:24" LastEditedBy="">
              <DefinitionLong/>
              <DefinitionShort>see {L:אְַבִי הָעֶזְרִי&lt;SDBH:אֲבִי הָעֶזְרִי&gt;}</DefinitionShort>
              <Glosses>
                <Gloss>Abiezrite</Gloss>
              </Glosses>
              <Comments/>
            </LEXSense>
          </LEXSenses>
          <LEXReferences>
            <LEXReference>00700601100032</LEXReference>
            <LEXReference>00700602400042</LEXReference>
            <LEXReference>00700803200034</LEXReference>
          </LEXReferences>
          <LEXVideos/>
        </LEXMeaning>
        <LEXMeaning Id="000003001016000" IsBiblicalTerm="N" EntryCode="" Indent="0">
          <LEXSenses>
            <LEXSense LanguageCode="en" LastEdited="2017-12-31 13:15:24" LastEditedBy="">
              <DefinitionLong/>
              <DefinitionShort>see {L:חוּרָם אָבִי&lt;SDBH:חוּרָם אָבִי&gt;}</DefinitionShort>
              <Glosses>
                <Gloss>Huram Abi</Gloss>
              </Glosses>
              <Comments/>
            </LEXSense>
          </LEXSenses>
          <LEXReferences>
            <LEXReference>01400201200020</LEXReference>
            <LEXReference>01400401600038</LEXReference>
          </LEXReferences>
          <LEXVideos/>
        </LEXMeaning>
      </LEXMeanings>
    </BaseForm>
  </BaseForms>
</Lexicon_Entry>