<?xml version="1.0" encoding="UTF-8" standalone="yes"?>
<Lexicon_Entry Id="001154000000000" Lemma="בַּר" Version="5" HasAramaic="true" InLXX="false" AlphaPos="ב">
  <StrongCodes>
    <Strong>A1247</Strong>
    <Strong>H1248</Strong>
    <Strong>H1249</Strong>
    <Strong>H1250</Strong>
    <Strong>A1251</Strong>
  </StrongCodes>
  <Authors>
    <Author>Enio R.Mueller</Author>
  </Authors>
  <Contributors/>
  <AlternateLemmas/>
  <MainLinks/>
  <Notes>
    <Note Caller="1" LanguageCode="en" LastEdited="" LastEditedBy="">
      <References>
        <Reference>01900201200004</Reference>
      </References>
      <Content>MT נַשְּׁקוּ־בַר | LXX "δράξασθε παιδείας" NETS "Seize upon instruction" | VUL "adorate pure" NJPS "pay homage in good faith" REB "worship with reverence" [2] or see {L:בֹּר&lt;SDBH:בֹּר&gt;} | NIV ESV "Kiss the Son" CEV "Show respect to (his) son" = [1] | RSV NJB NRSV "kiss his feet" = נַשְּׁקוּ בְּרַגְלָיו</Content>
    </Note>
  </Notes>
  <ContributorNote/>
  <BaseForms>
    <BaseForm Id="001154001000000">
      <PartsOfSpeech>
        <PartOfSpeech>nsm</PartOfSpeech>
      </PartsOfSpeech>
      <BaseFormLinks/>
      <LEXMeanings>
        <LEXMeaning Id="001154001001000" IsBiblicalTerm="M" EntryCode="" Indent="0">
          <LEXDomains>
            <LEXDomain Code="001001002003012">Relatives</LEXDomain>
          </LEXDomains>
          <LEXSenses>
            <LEXSense LanguageCode="en" LastEdited="2017-06-21 15:40:21" LastEditedBy="">
              <DefinitionLong/>
              <DefinitionShort>aramaism: = direct or indirect human offspring, either male or indeterminate, either biologically or through adoption</DefinitionShort>
              <Glosses>
                <Gloss>son</Gloss>
              </Glosses>
              <Comments/>
            </LEXSense>
          </LEXSenses>
          <LEXReferences>
            <LEXReference>01500500100016</LEXReference>
            <LEXReference>01500500200010</LEXReference>
            <LEXReference>01500500200018</LEXReference>
            <LEXReference>01500601400028</LEXReference>
            <LEXReference>01900201200004{N:001}</LEXReference>
            <LEXReference>02003100200004</LEXReference>
            <LEXReference>02003100200010</LEXReference>
            <LEXReference>02003100200018</LEXReference>
            <LEXReference>02700302500052</LEXReference>
            <LEXReference>02700502200010</LEXReference>
          </LEXReferences>
          <LEXVideos/>
          <LEXCoreDomains>
            <LEXCoreDomain Code="062">Family</LEXCoreDomain>
            <LEXCoreDomain Code="121">Parenthood</LEXCoreDomain>
            <LEXCoreDomain Code="129">Posterity</LEXCoreDomain>
          </LEXCoreDomains>
        </LEXMeaning>
        <LEXMeaning Id="001154001002000" IsBiblicalTerm="M" EntryCode="" Indent="0">
          <LEXDomains>
            <LEXDomain Code="002001001057" Source="Birth" SourceCode="002002002003">Stage</LEXDomain>
          </LEXDomains>
          <LEXSenses>
            <LEXSense LanguageCode="en" LastEdited="2017-12-19 19:12:42" LastEditedBy="">
              <DefinitionLong/>
              <DefinitionShort>= state in which humans and animals have a certain age, ◄ referred to as a child of a certain number of years</DefinitionShort>
              <Glosses>
                <Gloss>at the age of ...</Gloss>
              </Glosses>
              <Comments/>
            </LEXSense>
          </LEXSenses>
          <LEXReferences>
            <LEXReference>02700600100016</LEXReference>
          </LEXReferences>
          <LEXVideos/>
          <LEXCoreDomains>
            <LEXCoreDomain Code="005">Age</LEXCoreDomain>
          </LEXCoreDomains>
        </LEXMeaning>
        <LEXMeaning Id="001154001003000" IsBiblicalTerm="Y" EntryCode="" Indent="0">
          <LEXDomains>
            <LEXDomain Code="001001002003" Source="Birth" SourceCode="002002002003">People</LEXDomain>
          </LEXDomains>
          <LEXSenses>
            <LEXSense LanguageCode="en" LastEdited="2017-12-19 19:12:42" LastEditedBy="">
              <DefinitionLong/>
              <DefinitionShort>= member of a larger group of related people or objects, ◄ referred to as a child of that larger group</DefinitionShort>
              <Glosses>
                <Gloss>child &gt; part</Gloss>
              </Glosses>
              <Comments/>
            </LEXSense>
          </LEXSenses>
          <LEXReferences>
            <LEXReference>02700701300024</LEXReference>
          </LEXReferences>
          <LEXVideos/>
          <LEXCoreDomains>
            <LEXCoreDomain Code="038">Completeness</LEXCoreDomain>
          </LEXCoreDomains>
        </LEXMeaning>
      </LEXMeanings>
    </BaseForm>
    <BaseForm Id="001154002000000">
      <PartsOfSpeech>
        <PartOfSpeech>aj</PartOfSpeech>
      </PartsOfSpeech>
      <RelatedLemmas>
        <RelatedLemma>
          <Word>ברר</Word>
        </RelatedLemma>
      </RelatedLemmas>
      <BaseFormLinks/>
      <LEXMeanings>
        <LEXMeaning Id="001154002001000" IsBiblicalTerm="Y" EntryCode="" Indent="0">
          <LEXDomains>
            <LEXDomain Code="002002001017">Non-Space</LEXDomain>
          </LEXDomains>
          <LEXSenses>
            <LEXSense LanguageCode="en" LastEdited="2017-06-21 15:40:21" LastEditedBy="">
              <DefinitionLong/>
              <DefinitionShort>= state of being devoid of content</DefinitionShort>
              <Glosses>
                <Gloss>empty</Gloss>
              </Glosses>
              <Comments/>
            </LEXSense>
          </LEXSenses>
          <LEXReferences>
            <LEXReference>02001400400010</LEXReference>
          </LEXReferences>
          <LEXVideos/>
          <LEXCoreDomains>
            <LEXCoreDomain Code="039">Content</LEXCoreDomain>
          </LEXCoreDomains>
        </LEXMeaning>
        <LEXMeaning Id="001154002002000" IsBiblicalTerm="M" EntryCode="" Indent="0">
          <LEXDomains>
            <LEXDomain Code="001005002002001" Source="Non-Space" SourceCode="002002001017">Land</LEXDomain>
          </LEXDomains>
          <LEXSenses>
            <LEXSense LanguageCode="en" LastEdited="2017-06-21 15:40:21" LastEditedBy="">
              <DefinitionLong/>
              <DefinitionShort>= uncultivated, uninhabited land, ► where wild animals can live free</DefinitionShort>
              <Glosses>
                <Gloss>open field</Gloss>
              </Glosses>
              <Comments/>
            </LEXSense>
          </LEXSenses>
          <LEXReferences>
            <LEXReference>01803900400012</LEXReference>
            <LEXReference>02700203800020</LEXReference>
            <LEXReference>02700400900028</LEXReference>
            <LEXReference>02700401200034</LEXReference>
            <LEXReference>02700401800030</LEXReference>
            <LEXReference>02700402000066</LEXReference>
            <LEXReference>02700402000084</LEXReference>
            <LEXReference>02700402200018</LEXReference>
            <LEXReference>02700402900018</LEXReference>
          </LEXReferences>
          <LEXVideos/>
          <LEXCoreDomains>
            <LEXCoreDomain Code="097">Land</LEXCoreDomain>
          </LEXCoreDomains>
        </LEXMeaning>
        <LEXMeaning Id="001154002003000" IsBiblicalTerm="Y" EntryCode="" Indent="0">
          <LEXDomains>
            <LEXDomain Code="002001001028" Source="Non-Space" SourceCode="002002001017">Good</LEXDomain>
          </LEXDomains>
          <LEXSynonyms>
            <LEXSynonym>אָיֹם</LEXSynonym>
            <LEXSynonym>יָפֶה</LEXSynonym>
            <LEXSynonym>תָּם</LEXSynonym>
          </LEXSynonyms>
          <LEXSenses>
            <LEXSense LanguageCode="en" LastEdited="2017-06-21 15:40:21" LastEditedBy="">
              <DefinitionLong/>
              <DefinitionShort>= state in which humans possess a beauty that is not marred by anything</DefinitionShort>
              <Glosses>
                <Gloss>flawless</Gloss>
              </Glosses>
              <Comments/>
            </LEXSense>
          </LEXSenses>
          <LEXReferences>
            <LEXReference>02200600900018</LEXReference>
            <LEXReference>02200601000022</LEXReference>
          </LEXReferences>
          <LEXVideos/>
          <LEXCoreDomains>
            <LEXCoreDomain Code="016">Beauty</LEXCoreDomain>
          </LEXCoreDomains>
        </LEXMeaning>
        <LEXMeaning Id="001154002004000" IsBiblicalTerm="M" EntryCode="" Indent="0">
          <LEXDomains>
            <LEXDomain Code="002001003014" Source="Non-Happen" SourceCode="002002003004">Right</LEXDomain>
          </LEXDomains>
          <LEXSynonyms>
            <LEXSynonym>זַךְ</LEXSynonym>
            <LEXSynonym>יָשָׁר</LEXSynonym>
            <LEXSynonym>נָקִי</LEXSynonym>
          </LEXSynonyms>
          <LEXSenses>
            <LEXSense LanguageCode="en" LastEdited="2017-06-21 15:40:21" LastEditedBy="">
              <DefinitionLong/>
              <DefinitionShort>= state in which an event happens entirely as desired or required, without any interference that could be considered a flaw</DefinitionShort>
              <Glosses>
                <Gloss>pure</Gloss>
                <Gloss>flawless</Gloss>
              </Glosses>
              <Comments/>
            </LEXSense>
          </LEXSenses>
          <LEXReferences>
            <LEXReference>01801100400012</LEXReference>
            <LEXReference>01901900900016</LEXReference>
            <LEXReference>01902400400008</LEXReference>
            <LEXReference>01907300100020</LEXReference>
          </LEXReferences>
          <LEXVideos/>
          <LEXCoreDomains>
            <LEXCoreDomain Code="137">Quality</LEXCoreDomain>
          </LEXCoreDomains>
        </LEXMeaning>
      </LEXMeanings>
    </BaseForm>
    <BaseForm Id="001154003000000">
      <PartsOfSpeech>
        <PartOfSpeech>nsm</PartOfSpeech>
      </PartsOfSpeech>
      <BaseFormLinks/>
      <LEXMeanings>
        <LEXMeaning Id="001154003001000" IsBiblicalTerm="M" EntryCode="" Indent="0">
          <LEXDomains>
            <LEXDomain Code="001004003002">Crops</LEXDomain>
          </LEXDomains>
          <LEXSenses>
            <LEXSense LanguageCode="en" LastEdited="2017-06-21 15:40:21" LastEditedBy="">
              <DefinitionLong/>
              <DefinitionShort>collective: = seeds of cultivated cereal; ► used as the main ingredient for bread and related food products; ≈ regarded as an essential condition for life</DefinitionShort>
              <Glosses>
                <Gloss>grain</Gloss>
              </Glosses>
              <Comments/>
            </LEXSense>
          </LEXSenses>
          <LEXReferences>
            <LEXReference>00104103500032</LEXReference>
            <LEXReference>00104104900008</LEXReference>
            <LEXReference>00104200300016</LEXReference>
            <LEXReference>00104202500016</LEXReference>
            <LEXReference>00104502300034</LEXReference>
            <LEXReference>01906501400016</LEXReference>
            <LEXReference>01907201600006</LEXReference>
            <LEXReference>02001102600004</LEXReference>
            <LEXReference>02402302800042</LEXReference>
            <LEXReference>02900202400010</LEXReference>
            <LEXReference>03000501100016</LEXReference>
            <LEXReference>03000800500030</LEXReference>
            <LEXReference>03000800600028</LEXReference>
          </LEXReferences>
          <LEXVideos/>
          <LEXCoreDomains>
            <LEXCoreDomain Code="125">Plant</LEXCoreDomain>
            <LEXCoreDomain Code="069">Food</LEXCoreDomain>
          </LEXCoreDomains>
        </LEXMeaning>
      </LEXMeanings>
    </BaseForm>
  </BaseForms>
</Lexicon_Entry>