<?xml version="1.0" encoding="UTF-8" standalone="yes"?>
<Lexicon_Entry Id="004531000000000" Lemma="מַשָּׁק" Version="3" HasAramaic="false" InLXX="false" AlphaPos="מ">
  <StrongCodes>
    <Strong>H4944</Strong>
  </StrongCodes>
  <Authors>
    <Author>Reinier de Blois</Author>
  </Authors>
  <Contributors/>
  <AlternateLemmas/>
  <MainLinks/>
  <Notes/>
  <ContributorNote/>
  <BaseForms>
    <BaseForm Id="004531001000000">
      <PartsOfSpeech>
        <PartOfSpeech>nsm</PartOfSpeech>
      </PartsOfSpeech>
      <RelatedLemmas>
        <RelatedLemma>
          <Word>שׁקק</Word>
        </RelatedLemma>
      </RelatedLemmas>
      <BaseFormLinks/>
      <LEXMeanings>
        <LEXMeaning Id="004531001001000" IsBiblicalTerm="Y" EntryCode="" Indent="0">
          <LEXDomains>
            <LEXDomain Code="002002001011">Move</LEXDomain>
          </LEXDomains>
          <LEXForms>
            <LEXForm>vbqal-</LEXForm>
          </LEXForms>
          <LEXSenses>
            <LEXSense LanguageCode="en" LastEdited="2017-03-08 16:19:08" LastEditedBy="">
              <DefinitionLong/>
              <DefinitionShort>= process by which animals move forward at great speed and with aggressive intent</DefinitionShort>
              <Glosses>
                <Gloss>rushing upon</Gloss>
              </Glosses>
              <Comments/>
            </LEXSense>
          </LEXSenses>
          <LEXReferences>
            <LEXReference>02303300400016</LEXReference>
          </LEXReferences>
          <LEXVideos/>
        </LEXMeaning>
      </LEXMeanings>
    </BaseForm>
  </BaseForms>
</Lexicon_Entry>