<?xml version="1.0" encoding="UTF-8" standalone="yes"?>
<Lexicon_Entry Id="004699000000000" Lemma="נוס" Version="4" HasAramaic="false" InLXX="false" AlphaPos="נ">
  <StrongCodes>
    <Strong>H5127</Strong>
    <Strong>H5211</Strong>
  </StrongCodes>
  <Authors>
    <Author>Reinier de Blois</Author>
  </Authors>
  <Contributors/>
  <AlternateLemmas/>
  <MainLinks/>
  <Notes>
    <Note Caller="1" LanguageCode="en" LastEdited="" LastEditedBy="">
      <References>
        <Reference>02404804400004</Reference>
      </References>
      <Content>MT-K ניס | MT-Q נָס</Content>
    </Note>
  </Notes>
  <ContributorNote/>
  <BaseForms>
    <BaseForm Id="004699001000000">
      <PartsOfSpeech>
        <PartOfSpeech>vb</PartOfSpeech>
      </PartsOfSpeech>
      <RelatedLemmas>
        <RelatedLemma>
          <Word>מָנֹוס</Word>
        </RelatedLemma>
        <RelatedLemma>
          <Word>מְנוּסָה</Word>
        </RelatedLemma>
        <RelatedLemma>
          <Word>נסס</Word>
        </RelatedLemma>
      </RelatedLemmas>
      <BaseFormLinks/>
      <LEXMeanings>
        <LEXMeaning Id="004699001001000" IsBiblicalTerm="Y" EntryCode="" Indent="0">
          <LEXDomains>
            <LEXDomain Code="002002001006">Flee</LEXDomain>
          </LEXDomains>
          <LEXForms>
            <LEXForm>vbqal-</LEXForm>
          </LEXForms>
          <LEXSenses>
            <LEXSense LanguageCode="en" LastEdited="2017-11-11 09:21:11" LastEditedBy="">
              <DefinitionLong/>
              <DefinitionShort>= action by which humans move to another place in haste, ► in order to escape from a dangerous situation</DefinitionShort>
              <Glosses>
                <Gloss>to flee</Gloss>
              </Glosses>
              <Comments/>
            </LEXSense>
          </LEXSenses>
          <LEXReferences>
            <LEXReference>00101401000018</LEXReference>
            <LEXReference>00101401000042</LEXReference>
            <LEXReference>00101902000018</LEXReference>
            <LEXReference>00103901200030</LEXReference>
            <LEXReference>00103901300022</LEXReference>
            <LEXReference>00103901500030</LEXReference>
            <LEXReference>00103901800026</LEXReference>
            <LEXReference>00200400300026</LEXReference>
            <LEXReference>00201402500026</LEXReference>
            <LEXReference>00201402700040</LEXReference>
            <LEXReference>00202101300032</LEXReference>
            <LEXReference>00302601700030</LEXReference>
            <LEXReference>00302603600040</LEXReference>
            <LEXReference>00401003500032</LEXReference>
            <LEXReference>00401603400012</LEXReference>
            <LEXReference>00403500600036</LEXReference>
            <LEXReference>00403501100020</LEXReference>
            <LEXReference>00403501500046</LEXReference>
            <LEXReference>00403502500044</LEXReference>
            <LEXReference>00403502600024</LEXReference>
            <LEXReference>00403503200012</LEXReference>
            <LEXReference>00500404200004</LEXReference>
            <LEXReference>00500404200042</LEXReference>
            <LEXReference>00501900300034</LEXReference>
            <LEXReference>00501900400014</LEXReference>
            <LEXReference>00501900500072</LEXReference>
            <LEXReference>00501901100040</LEXReference>
            <LEXReference>00502800700040</LEXReference>
            <LEXReference>00502802500032</LEXReference>
            <LEXReference>00503400700030</LEXReference>
            <LEXReference>00600700400024</LEXReference>
            <LEXReference>00600800500050</LEXReference>
            <LEXReference>00600800600024</LEXReference>
            <LEXReference>00600800600042</LEXReference>
            <LEXReference>00600801500020</LEXReference>
            <LEXReference>00600802000046</LEXReference>
            <LEXReference>00600802000062</LEXReference>
            <LEXReference>00601001100008</LEXReference>
            <LEXReference>00601001600004</LEXReference>
            <LEXReference>00602000300004</LEXReference>
            <LEXReference>00602000400004</LEXReference>
            <LEXReference>00602000600090</LEXReference>
            <LEXReference>00602000900038</LEXReference>
            <LEXReference>00700100600004</LEXReference>
            <LEXReference>00700401500060</LEXReference>
            <LEXReference>00700401700006</LEXReference>
            <LEXReference>00700702100034</LEXReference>
            <LEXReference>00700702100038</LEXReference>
            <LEXReference>00700702200042</LEXReference>
            <LEXReference>00700801200004</LEXReference>
            <LEXReference>00700902100004</LEXReference>
            <LEXReference>00700904000010</LEXReference>
            <LEXReference>00700905100020</LEXReference>
            <LEXReference>00702003200034</LEXReference>
            <LEXReference>00702004500008</LEXReference>
            <LEXReference>00702004700008</LEXReference>
            <LEXReference>00900401000016</LEXReference>
            <LEXReference>00900401600036</LEXReference>
            <LEXReference>00900401700014</LEXReference>
            <LEXReference>00901402200024</LEXReference>
            <LEXReference>00901702400022</LEXReference>
            <LEXReference>00901705100064</LEXReference>
            <LEXReference>00901900800042</LEXReference>
            <LEXReference>00901901000060</LEXReference>
            <LEXReference>00903001700060</LEXReference>
            <LEXReference>00903100100014</LEXReference>
            <LEXReference>00903100700034</LEXReference>
            <LEXReference>00903100700064</LEXReference>
            <LEXReference>01000100400030</LEXReference>
            <LEXReference>01000400400050</LEXReference>
            <LEXReference>01000400400062</LEXReference>
            <LEXReference>01001001300030</LEXReference>
            <LEXReference>01001001400012</LEXReference>
            <LEXReference>01001001400018</LEXReference>
            <LEXReference>01001001800004</LEXReference>
            <LEXReference>01001302900046</LEXReference>
            <LEXReference>01001700200028</LEXReference>
            <LEXReference>01001800300018</LEXReference>
            <LEXReference>01001800300020</LEXReference>
            <LEXReference>01001801700052</LEXReference>
            <LEXReference>01001900400044</LEXReference>
            <LEXReference>01001900900072</LEXReference>
            <LEXReference>01002301100048</LEXReference>
            <LEXReference>01002401300046</LEXReference>
            <LEXReference>01100202800036</LEXReference>
            <LEXReference>01100202900016</LEXReference>
            <LEXReference>01101201800062</LEXReference>
            <LEXReference>01102002000012</LEXReference>
            <LEXReference>01102003000004</LEXReference>
            <LEXReference>01102003000046</LEXReference>
            <LEXReference>01200302400028</LEXReference>
            <LEXReference>01200700700008</LEXReference>
            <LEXReference>01200700700048</LEXReference>
            <LEXReference>01200802100056</LEXReference>
            <LEXReference>01200900300050</LEXReference>
            <LEXReference>01200901000036</LEXReference>
            <LEXReference>01200902300012</LEXReference>
            <LEXReference>01200902700014</LEXReference>
            <LEXReference>01200902700056</LEXReference>
            <LEXReference>01201401200016</LEXReference>
            <LEXReference>01201401900016</LEXReference>
            <LEXReference>01301000100014</LEXReference>
            <LEXReference>01301000700022</LEXReference>
            <LEXReference>01301000700044</LEXReference>
            <LEXReference>01301101300052</LEXReference>
            <LEXReference>01301901400032</LEXReference>
            <LEXReference>01301901500012</LEXReference>
            <LEXReference>01301901500018</LEXReference>
            <LEXReference>01301901800004</LEXReference>
            <LEXReference>01401001800062</LEXReference>
            <LEXReference>01401301600004</LEXReference>
            <LEXReference>01401401100030</LEXReference>
            <LEXReference>01402502200016</LEXReference>
            <LEXReference>01402502700034</LEXReference>
            <LEXReference>01906800200012</LEXReference>
            <LEXReference>01910400700006</LEXReference>
            <LEXReference>01911400300010</LEXReference>
            <LEXReference>01911400500012</LEXReference>
            <LEXReference>02002800100002</LEXReference>
            <LEXReference>02002801700016</LEXReference>
            <LEXReference>02200201700014</LEXReference>
            <LEXReference>02200400600014</LEXReference>
            <LEXReference>02301000300030</LEXReference>
            <LEXReference>02301002900022</LEXReference>
            <LEXReference>02301301400040</LEXReference>
            <LEXReference>02301701300022</LEXReference>
            <LEXReference>02302000600034</LEXReference>
            <LEXReference>02302401800008</LEXReference>
            <LEXReference>02303001600014</LEXReference>
            <LEXReference>02303001600020</LEXReference>
            <LEXReference>02303001700022</LEXReference>
            <LEXReference>02303100800028</LEXReference>
            <LEXReference>02303501000040</LEXReference>
            <LEXReference>02305101100038</LEXReference>
            <LEXReference>02404600500024</LEXReference>
            <LEXReference>02404600600004</LEXReference>
            <LEXReference>02404602100024</LEXReference>
            <LEXReference>02404800600002</LEXReference>
            <LEXReference>02404801900018</LEXReference>
            <LEXReference>02404804400004{N:001}</LEXReference>
            <LEXReference>02404804400008</LEXReference>
            <LEXReference>02404804500014</LEXReference>
            <LEXReference>02404900800002</LEXReference>
            <LEXReference>02404902400010</LEXReference>
            <LEXReference>02404903000002</LEXReference>
            <LEXReference>02405001600048</LEXReference>
            <LEXReference>02405002800004</LEXReference>
            <LEXReference>02405100600002</LEXReference>
            <LEXReference>03000201600016</LEXReference>
            <LEXReference>03000501900006</LEXReference>
            <LEXReference>03000900100058</LEXReference>
            <LEXReference>03000900100062</LEXReference>
            <LEXReference>03400200900022</LEXReference>
            <LEXReference>03800201000008</LEXReference>
            <LEXReference>03801400500004</LEXReference>
            <LEXReference>03801400500024</LEXReference>
            <LEXReference>03801400500030</LEXReference>
          </LEXReferences>
          <LEXVideos/>
          <LEXCoreDomains>
            <LEXCoreDomain Code="110">Motion</LEXCoreDomain>
            <LEXCoreDomain Code="152">Security</LEXCoreDomain>
          </LEXCoreDomains>
        </LEXMeaning>
        <LEXMeaning Id="004699001002000" IsBiblicalTerm="Y" EntryCode="" Indent="0">
          <LEXDomains>
            <LEXDomain Code="002002001006">Flee</LEXDomain>
          </LEXDomains>
          <LEXForms>
            <LEXForm>vbhif-</LEXForm>
          </LEXForms>
          <LEXSenses>
            <LEXSense LanguageCode="en" LastEdited="2017-11-11 09:21:11" LastEditedBy="">
              <DefinitionLong/>
              <DefinitionShort>= causative action by which humans cause other humans to move to another place in haste, ► in order to escape from a dangerous situation</DefinitionShort>
              <Glosses>
                <Gloss>to put to flight</Gloss>
                <Gloss>to cause to flee</Gloss>
              </Glosses>
              <Comments/>
            </LEXSense>
          </LEXSenses>
          <LEXReferences>
            <LEXReference>00200902000018</LEXReference>
            <LEXReference>00503203000014</LEXReference>
          </LEXReferences>
          <LEXVideos/>
          <LEXCoreDomains>
            <LEXCoreDomain Code="110">Motion</LEXCoreDomain>
            <LEXCoreDomain Code="152">Security</LEXCoreDomain>
          </LEXCoreDomains>
        </LEXMeaning>
        <LEXMeaning Id="004699001003000" IsBiblicalTerm="Y" EntryCode="" Indent="0">
          <LEXDomains>
            <LEXDomain Code="002002001007" Source="Flee" SourceCode="002002001006">Flow</LEXDomain>
          </LEXDomains>
          <LEXForms>
            <LEXForm>vbpiel</LEXForm>
          </LEXForms>
          <LEXSenses>
            <LEXSense LanguageCode="en" LastEdited="2017-11-11 09:21:11" LastEditedBy="">
              <DefinitionLong/>
              <DefinitionShort>literally: to cause to flee; hence: = process by which wind causes water to flow into a certain direction</DefinitionShort>
              <Glosses>
                <Gloss>to drive</Gloss>
              </Glosses>
              <Comments/>
            </LEXSense>
          </LEXSenses>
          <LEXReferences>
            <LEXReference>02305901900044</LEXReference>
          </LEXReferences>
          <LEXVideos/>
          <LEXCoreDomains>
            <LEXCoreDomain Code="101">Liquids</LEXCoreDomain>
          </LEXCoreDomains>
        </LEXMeaning>
        <LEXMeaning Id="004699001004000" IsBiblicalTerm="Y" EntryCode="" Indent="0">
          <LEXDomains>
            <LEXDomain Code="002003003018" Source="Flee" SourceCode="002002001006">Safe</LEXDomain>
          </LEXDomains>
          <LEXForms>
            <LEXForm>vbhif-</LEXForm>
          </LEXForms>
          <LEXSenses>
            <LEXSense LanguageCode="en" LastEdited="2017-11-11 09:21:11" LastEditedBy="">
              <DefinitionLong/>
              <DefinitionShort>literally: to cause to flee; hence: = causative action by which humans cause objects to be safe from danger</DefinitionShort>
              <Glosses>
                <Gloss>to keep safe</Gloss>
              </Glosses>
              <Comments/>
            </LEXSense>
          </LEXSenses>
          <LEXReferences>
            <LEXReference>00700601100056</LEXReference>
          </LEXReferences>
          <LEXVideos/>
          <LEXCoreDomains>
            <LEXCoreDomain Code="152">Security</LEXCoreDomain>
          </LEXCoreDomains>
        </LEXMeaning>
      </LEXMeanings>
    </BaseForm>
  </BaseForms>
</Lexicon_Entry>