<?xml version="1.0" encoding="UTF-8" standalone="yes"?>
<Lexicon_Entry Id="006314000000000" Lemma="צֵר" Version="5" HasAramaic="false" InLXX="false" AlphaPos="צ">
  <StrongCodes>
    <Strong>H6863</Strong>
  </StrongCodes>
  <Authors>
    <Author>Graham S. Ogden</Author>
  </Authors>
  <Contributors/>
  <AlternateLemmas/>
  <MainLinks/>
  <Notes>
    <Note Caller="1" LanguageCode="en" LastEdited="" LastEditedBy="">
      <References>
        <Reference>00601903500012</Reference>
      </References>
      <Content>MT RSV NIV NJPS NJB NRSV REB GNT CEV | LXX Τύρος "Tyre"</Content>
    </Note>
  </Notes>
  <ContributorNote/>
  <BaseForms>
    <BaseForm Id="006314001000000">
      <PartsOfSpeech>
        <PartOfSpeech>np</PartOfSpeech>
      </PartsOfSpeech>
      <BaseFormLinks/>
      <LEXMeanings>
        <LEXMeaning Id="006314001001000" IsBiblicalTerm="Y" EntryCode="" Indent="0">
          <LEXDomains>
            <LEXDomain Code="003001010">Names of Locations</LEXDomain>
          </LEXDomains>
          <LEXSenses>
            <LEXSense LanguageCode="en" LastEdited="2015-11-16 23:36:56" LastEditedBy="">
              <DefinitionLong/>
              <DefinitionShort>= fortified town; ◄ territory of {L:Naphtali&lt;SDBH:נַפְתָּלִי&gt;}</DefinitionShort>
              <Glosses>
                <Gloss>Zer</Gloss>
              </Glosses>
              <Comments/>
            </LEXSense>
          </LEXSenses>
          <LEXReferences>
            <LEXReference>00601903500012{N:001}</LEXReference>
          </LEXReferences>
          <LEXVideos/>
          <LEXCoordinates>
            <LEXCoordinates>33.125828,35.165000</LEXCoordinates>
          </LEXCoordinates>
        </LEXMeaning>
      </LEXMeanings>
    </BaseForm>
  </BaseForms>
</Lexicon_Entry>