<?xml version="1.0" encoding="UTF-8" standalone="yes"?>
<Lexicon_Entry Id="006968000000000" Lemma="שׂבע" Version="4" HasAramaic="false" InLXX="false" AlphaPos="ש">
  <StrongCodes>
    <Strong>H7646</Strong>
  </StrongCodes>
  <Authors>
    <Author>Reinier de Blois</Author>
  </Authors>
  <Contributors/>
  <AlternateLemmas/>
  <MainLinks/>
  <Notes/>
  <ContributorNote/>
  <BaseForms>
    <BaseForm Id="006968001000000">
      <PartsOfSpeech>
        <PartOfSpeech>vb</PartOfSpeech>
      </PartsOfSpeech>
      <RelatedLemmas>
        <RelatedLemma>
          <Word>שָׂבֵעַ</Word>
        </RelatedLemma>
        <RelatedLemma>
          <Word>שָׂבָע</Word>
        </RelatedLemma>
        <RelatedLemma>
          <Word>שֹׂבַע</Word>
        </RelatedLemma>
        <RelatedLemma>
          <Word>שִׂבְעָה</Word>
        </RelatedLemma>
        <RelatedLemma>
          <Word>שָׂבְעָה</Word>
        </RelatedLemma>
      </RelatedLemmas>
      <BaseFormLinks/>
      <LEXMeanings>
        <LEXMeaning Id="006968001001000" IsBiblicalTerm="Y" EntryCode="" Indent="0">
          <LEXDomains>
            <LEXDomain Code="002001001024">Ingest</LEXDomain>
          </LEXDomains>
          <LEXForms>
            <LEXForm>vbqal-</LEXForm>
          </LEXForms>
          <LEXSynonyms>
            <LEXSynonym>אכל</LEXSynonym>
          </LEXSynonyms>
          <LEXSenses>
            <LEXSense LanguageCode="en" LastEdited="2017-08-10 13:28:29" LastEditedBy="">
              <DefinitionLong/>
              <DefinitionShort>= process by which someone's desire for food is fulfilled</DefinitionShort>
              <Glosses>
                <Gloss>to be satiated</Gloss>
                <Gloss>to become satiated</Gloss>
              </Glosses>
              <Comments/>
            </LEXSense>
          </LEXSenses>
          <LEXReferences>
            <LEXReference>00201600800040</LEXReference>
            <LEXReference>00201601200038</LEXReference>
            <LEXReference>00302602600048</LEXReference>
            <LEXReference>00500601100048</LEXReference>
            <LEXReference>00500801000008</LEXReference>
            <LEXReference>00500801200008</LEXReference>
            <LEXReference>00501101500022</LEXReference>
            <LEXReference>00501402900054</LEXReference>
            <LEXReference>00502601200074</LEXReference>
            <LEXReference>00503102000034</LEXReference>
            <LEXReference>00800201400070</LEXReference>
            <LEXReference>01403101000048</LEXReference>
            <LEXReference>01600902500054</LEXReference>
            <LEXReference>01801902200018</LEXReference>
            <LEXReference>01802701400018</LEXReference>
            <LEXReference>01902202700008</LEXReference>
            <LEXReference>01903701900020</LEXReference>
            <LEXReference>01905901600016</LEXReference>
            <LEXReference>01906300600010</LEXReference>
            <LEXReference>01907802900008</LEXReference>
            <LEXReference>01910401300016</LEXReference>
            <LEXReference>01910401600002</LEXReference>
            <LEXReference>01910402800012</LEXReference>
            <LEXReference>02000103100018</LEXReference>
            <LEXReference>02001201100006</LEXReference>
            <LEXReference>02001401400006</LEXReference>
            <LEXReference>02001802000010</LEXReference>
            <LEXReference>02001802000018</LEXReference>
            <LEXReference>02002001300016</LEXReference>
            <LEXReference>02002501600012</LEXReference>
            <LEXReference>02002702000014</LEXReference>
            <LEXReference>02002702000026</LEXReference>
            <LEXReference>02002801900006</LEXReference>
            <LEXReference>02003000900004</LEXReference>
            <LEXReference>02003001500020</LEXReference>
            <LEXReference>02003001600014</LEXReference>
            <LEXReference>02003002200016</LEXReference>
            <LEXReference>02100100800022</LEXReference>
            <LEXReference>02300901900026</LEXReference>
            <LEXReference>02304401600024</LEXReference>
            <LEXReference>02404401700078</LEXReference>
            <LEXReference>02404601000040</LEXReference>
            <LEXReference>02500500600012</LEXReference>
            <LEXReference>02603902000004</LEXReference>
            <LEXReference>02800401000010</LEXReference>
            <LEXReference>02801300600008</LEXReference>
            <LEXReference>02801300600010</LEXReference>
            <LEXReference>02900201900042</LEXReference>
            <LEXReference>02900202600010</LEXReference>
            <LEXReference>03000400800028</LEXReference>
            <LEXReference>03300601400010</LEXReference>
            <LEXReference>03500200500048</LEXReference>
          </LEXReferences>
          <LEXVideos/>
          <LEXCoreDomains>
            <LEXCoreDomain Code="069">Food</LEXCoreDomain>
          </LEXCoreDomains>
        </LEXMeaning>
        <LEXMeaning Id="006968001002000" IsBiblicalTerm="Y" EntryCode="" Indent="0">
          <LEXDomains>
            <LEXDomain Code="002001001024">Ingest</LEXDomain>
          </LEXDomains>
          <LEXForms>
            <LEXForm>vbhif-</LEXForm>
            <LEXForm>vbpiel</LEXForm>
            <LEXForm>vbnif- (passive)</LEXForm>
          </LEXForms>
          <LEXSynonyms>
            <LEXSynonym>אכל</LEXSynonym>
          </LEXSynonyms>
          <LEXSenses>
            <LEXSense LanguageCode="en" LastEdited="2017-08-10 13:28:29" LastEditedBy="">
              <DefinitionLong/>
              <DefinitionShort>= causative process by which humans or deities cause the desire of (other) humans to be fulfilled</DefinitionShort>
              <Glosses>
                <Gloss>to satisfy (someone with food)</Gloss>
              </Glosses>
              <Comments/>
            </LEXSense>
          </LEXSenses>
          <LEXReferences>
            <LEXReference>01803103100022</LEXReference>
            <LEXReference>01803802700004</LEXReference>
            <LEXReference>01908101700020</LEXReference>
            <LEXReference>01910504000016</LEXReference>
            <LEXReference>01910700900004</LEXReference>
            <LEXReference>01913201500010</LEXReference>
            <LEXReference>01914701400014</LEXReference>
            <LEXReference>02400500700030</LEXReference>
            <LEXReference>02600701900048</LEXReference>
            <LEXReference>02603200400038</LEXReference>
          </LEXReferences>
          <LEXVideos/>
          <LEXCoreDomains>
            <LEXCoreDomain Code="069">Food</LEXCoreDomain>
          </LEXCoreDomains>
        </LEXMeaning>
        <LEXMeaning Id="006968001003000" IsBiblicalTerm="Y" EntryCode="" Indent="0">
          <LEXDomains>
            <LEXDomain Code="002003003010" Source="Ingest" SourceCode="002001001024">Engage</LEXDomain>
          </LEXDomains>
          <LEXForms>
            <LEXForm>vbqal-</LEXForm>
          </LEXForms>
          <LEXSenses>
            <LEXSense LanguageCode="en" LastEdited="2017-08-10 13:28:29" LastEditedBy="">
              <DefinitionLong/>
              <DefinitionShort>literally: to be satiated (with an event); hence: = process by which humans become more than fully engaged in a certain process or activity, which can be either good or bad</DefinitionShort>
              <Glosses>
                <Gloss>to be satisfied (with something)</Gloss>
                <Gloss>to have one's fill (of something)</Gloss>
              </Glosses>
              <Comments/>
            </LEXSense>
          </LEXSenses>
          <LEXReferences>
            <LEXReference>01800700400022</LEXReference>
            <LEXReference>01901701500012</LEXReference>
            <LEXReference>01906500500014</LEXReference>
            <LEXReference>01908800400004</LEXReference>
            <LEXReference>01912300300012</LEXReference>
            <LEXReference>01912300400004</LEXReference>
            <LEXReference>02001201400010</LEXReference>
            <LEXReference>02002801900016</LEXReference>
            <LEXReference>02100600300036</LEXReference>
            <LEXReference>02403101400022</LEXReference>
            <LEXReference>02500303000010</LEXReference>
            <LEXReference>03500201600002</LEXReference>
          </LEXReferences>
          <LEXVideos/>
        </LEXMeaning>
        <LEXMeaning Id="006968001004000" IsBiblicalTerm="Y" EntryCode="" Indent="0">
          <LEXDomains>
            <LEXDomain Code="002003003010" Source="Ingest" SourceCode="002001001024">Engage</LEXDomain>
          </LEXDomains>
          <LEXForms>
            <LEXForm>vbhif-</LEXForm>
          </LEXForms>
          <LEXSenses>
            <LEXSense LanguageCode="en" LastEdited="2017-08-10 13:28:29" LastEditedBy="">
              <DefinitionLong/>
              <DefinitionShort>literally: to cause to be satiated (with an event); hence: = causative process by which deities cause humans to become more than fully engaged in a certain process or activity, which can be either good or bad</DefinitionShort>
              <Glosses>
                <Gloss>to satisfy</Gloss>
                <Gloss>to give (people their) fill (of something)</Gloss>
              </Glosses>
              <Comments/>
            </LEXSense>
          </LEXSenses>
          <LEXReferences>
            <LEXReference>01800901800012</LEXReference>
            <LEXReference>01909001400002</LEXReference>
            <LEXReference>01909101600006</LEXReference>
            <LEXReference>01910300500004</LEXReference>
            <LEXReference>02500301500002</LEXReference>
          </LEXReferences>
          <LEXVideos/>
        </LEXMeaning>
        <LEXMeaning Id="006968001005000" IsBiblicalTerm="Y" EntryCode="" Indent="0">
          <LEXDomains>
            <LEXDomain Code="002001002014" Source="Ingest" SourceCode="002001001024">Hate</LEXDomain>
          </LEXDomains>
          <LEXForms>
            <LEXForm>vbqal-</LEXForm>
          </LEXForms>
          <LEXSynonyms>
            <LEXSynonym>שׂנא</LEXSynonym>
          </LEXSynonyms>
          <LEXAntonyms>
            <LEXAntonym>חפץ</LEXAntonym>
          </LEXAntonyms>
          <LEXSenses>
            <LEXSense LanguageCode="en" LastEdited="2017-08-10 13:28:29" LastEditedBy="">
              <DefinitionLong/>
              <DefinitionShort>literally: to be satiated (with someone or something); hence: = state in which humans or deities are strongly displeased with people or activities</DefinitionShort>
              <Glosses>
                <Gloss>to have enough (of someone or something)</Gloss>
              </Glosses>
              <Comments/>
            </LEXSense>
          </LEXSenses>
          <LEXReferences>
            <LEXReference>02002501700014</LEXReference>
            <LEXReference>02300101100014</LEXReference>
          </LEXReferences>
          <LEXVideos/>
          <LEXCoreDomains>
            <LEXCoreDomain Code="004">Affection</LEXCoreDomain>
          </LEXCoreDomains>
        </LEXMeaning>
        <LEXMeaning Id="006968001006000" IsBiblicalTerm="Y" EntryCode="" Indent="0">
          <LEXDomains>
            <LEXDomain Code="002001001038" Source="Ingest" SourceCode="002001001024">Old</LEXDomain>
          </LEXDomains>
          <LEXForms>
            <LEXForm>vbqal-</LEXForm>
          </LEXForms>
          <LEXCollocations>
            <LEXCollocation>שׂבע יָמִים</LEXCollocation>
          </LEXCollocations>
          <LEXSenses>
            <LEXSense LanguageCode="en" LastEdited="2017-08-10 13:28:29" LastEditedBy="">
              <DefinitionLong/>
              <DefinitionShort>literally: to be satiated with days; hence: = process by which humans live to a very old age</DefinitionShort>
              <Glosses>
                <Gloss>to be full (of days) &gt; to live long</Gloss>
              </Glosses>
              <Comments/>
            </LEXSense>
          </LEXSenses>
          <LEXReferences>
            <LEXReference>01302300100010</LEXReference>
            <LEXReference>01402401500010</LEXReference>
          </LEXReferences>
          <LEXVideos/>
          <LEXCoreDomains>
            <LEXCoreDomain Code="005">Age</LEXCoreDomain>
          </LEXCoreDomains>
        </LEXMeaning>
        <LEXMeaning Id="006968001007000" IsBiblicalTerm="Y" EntryCode="" Indent="0">
          <LEXDomains>
            <LEXDomain Code="002003002020" Source="Ingest" SourceCode="002001001024">Possess</LEXDomain>
          </LEXDomains>
          <LEXForms>
            <LEXForm>vbqal-</LEXForm>
          </LEXForms>
          <LEXSenses>
            <LEXSense LanguageCode="en" LastEdited="2022-04-16 14:48:42" LastEditedBy="">
              <DefinitionLong/>
              <DefinitionShort>literally: to be satisfied; hence: = action by which humans take possession of objects until they are satisfied</DefinitionShort>
              <Glosses>
                <Gloss>to take (one's) fill</Gloss>
              </Glosses>
              <Comments/>
            </LEXSense>
          </LEXSenses>
          <LEXReferences>
            <LEXReference>02000501000004</LEXReference>
          </LEXReferences>
          <LEXVideos/>
        </LEXMeaning>
        <LEXMeaning Id="006968001008000" IsBiblicalTerm="Y" EntryCode="" Indent="0">
          <LEXDomains>
            <LEXDomain Code="002001002023" Source="Ingest" SourceCode="002001001024">Relief</LEXDomain>
          </LEXDomains>
          <LEXForms>
            <LEXForm>vbqal-</LEXForm>
          </LEXForms>
          <LEXSenses>
            <LEXSense LanguageCode="en" LastEdited="2017-08-10 13:28:29" LastEditedBy="">
              <DefinitionLong/>
              <DefinitionShort>literally: to be satiated; hence: = process by which the desire of humans is fulfilled</DefinitionShort>
              <Glosses>
                <Gloss>to have (one's) fill &gt; to be contented</Gloss>
              </Glosses>
              <Comments/>
            </LEXSense>
          </LEXSenses>
          <LEXReferences>
            <LEXReference>01901701400038</LEXReference>
            <LEXReference>02100400800044</LEXReference>
            <LEXReference>02100500900008</LEXReference>
            <LEXReference>02305301100010</LEXReference>
            <LEXReference>02306601100008</LEXReference>
            <LEXReference>02405001000016</LEXReference>
            <LEXReference>02405001900042</LEXReference>
            <LEXReference>02601602800028</LEXReference>
            <LEXReference>02601602900028</LEXReference>
          </LEXReferences>
          <LEXVideos/>
        </LEXMeaning>
        <LEXMeaning Id="006968001009000" IsBiblicalTerm="Y" EntryCode="" Indent="0">
          <LEXDomains>
            <LEXDomain Code="002001002023" Source="Ingest" SourceCode="002001001024">Relief</LEXDomain>
          </LEXDomains>
          <LEXForms>
            <LEXForm>vbhif-</LEXForm>
            <LEXForm>vbpiel</LEXForm>
          </LEXForms>
          <LEXSenses>
            <LEXSense LanguageCode="en" LastEdited="2017-08-10 13:28:29" LastEditedBy="">
              <DefinitionLong/>
              <DefinitionShort>NO DATA YET</DefinitionShort>
              <Glosses>
                <Gloss>to give (one's) fill &gt; to make contented</Gloss>
              </Glosses>
              <Comments/>
            </LEXSense>
          </LEXSenses>
          <LEXReferences>
            <LEXReference>01914501600010</LEXReference>
            <LEXReference>02305801000020</LEXReference>
            <LEXReference>02305801100012</LEXReference>
            <LEXReference>02602703300012</LEXReference>
          </LEXReferences>
          <LEXVideos/>
          <LEXCoreDomains>
            <LEXCoreDomain Code="093">Joy and Grief</LEXCoreDomain>
          </LEXCoreDomains>
        </LEXMeaning>
      </LEXMeanings>
    </BaseForm>
  </BaseForms>
</Lexicon_Entry>